runs/web_b5258d7e4ad0_optimize_20260914T144523Z/round_3/attempt_2/candidate_1/formal/equiv_bmc/src/gold_gate.v
/* Generated by Yosys 0.68+195 (git sha1 435977e97-dirty, Release, Clang /usr/bin/clang++ 21.1.8) */

module gate(clk, rst, in_valid, in_data, out_valid, out_data);
  input clk;
  wire clk;
  input rst;
  wire rst;
  input in_valid;
  wire in_valid;
  input signed [7:0] in_data;
  wire signed [7:0] in_data;
  output out_valid;
  reg out_valid;
  output signed [18:0] out_data;
  reg signed [18:0] out_data;
  wire [18:0] _00_;
  wire _01_;
  wire [18:0] _02_;
  wire [18:0] _03_;
  wire [18:0] _04_;
  wire [18:0] _05_;
  wire [18:0] _06_;
  wire [18:0] _07_;
  wire [7:0] _08_;
  wire [7:0] _09_;
  wire [7:0] _10_;
  wire [7:0] _11_;
  wire [7:0] _12_;
  wire [7:0] _13_;
  wire _14_;
  wire _15_;
  wire [7:0] _16_;
  wire [7:0] _17_;
  wire [7:0] _18_;
  wire [7:0] _19_;
  wire [7:0] _20_;
  wire [7:0] _21_;
  wire signed [18:0] p0;
  reg signed [18:0] p0_r;
  wire signed [18:0] p1;
  reg signed [18:0] p1_r;
  wire signed [18:0] p2;
  reg signed [18:0] p2_r;
  wire signed [18:0] p3;
  reg signed [18:0] p3_r;
  wire signed [18:0] p4;
  reg signed [18:0] p4_r;
  wire signed [18:0] p5;
  reg signed [18:0] p5_r;
  wire signed [18:0] s1;
  wire signed [18:0] s2;
  wire signed [18:0] s3;
  wire signed [18:0] s4;
  wire signed [18:0] s5;
  reg signed [7:0] t0;
  reg signed [7:0] t1;
  reg signed [7:0] t2;
  reg signed [7:0] t3;
  reg signed [7:0] t4;
  reg signed [7:0] t5;
  reg vld;
  reg vld2;
  assign s1 = $signed(p0_r) + $signed(p1_r);
  assign s2 = $signed(s1) + $signed(p2_r);
  assign s3 = $signed(s2) + $signed(p3_r);
  assign s4 = $signed(s3) + $signed(p4_r);
  assign s5 = $signed(s4) + $signed(p5_r);
  assign p0 = $signed(t0) * $signed(8'h17);
  assign p1 = $signed(t1) * $signed(8'hd1);
  assign p2 = $signed(t2) * $signed(8'h51);
  assign p3 = $signed(t3) * $signed(8'h51);
  assign p4 = $signed(t4) * $signed(8'hd1);
  assign p5 = $signed(t5) * $signed(8'h17);
  always @(posedge clk)
    out_valid <= _01_;
  always @(posedge clk)
    out_data <= _00_;
  always @(posedge clk)
    p5_r <= _07_;
  always @(posedge clk)
    p4_r <= _06_;
  always @(posedge clk)
    p3_r <= _05_;
  always @(posedge clk)
    p2_r <= _04_;
  always @(posedge clk)
    p1_r <= _03_;
  always @(posedge clk)
    p0_r <= _02_;
  always @(posedge clk)
    vld2 <= _14_;
  always @(posedge clk)
    vld <= _15_;
  always @(posedge clk)
    t0 <= _08_;
  always @(posedge clk)
    t1 <= _09_;
  always @(posedge clk)
    t2 <= _10_;
  always @(posedge clk)
    t3 <= _11_;
  always @(posedge clk)
    t4 <= _12_;
  always @(posedge clk)
    t5 <= _13_;
  assign _01_ = rst ? 1'h0 : vld2;
  assign _00_ = rst ? 19'h00000 : s5;
  assign _14_ = rst ? 1'h0 : vld;
  assign _07_ = rst ? 19'h00000 : p5;
  assign _06_ = rst ? 19'h00000 : p4;
  assign _05_ = rst ? 19'h00000 : p3;
  assign _04_ = rst ? 19'h00000 : p2;
  assign _03_ = rst ? 19'h00000 : p1;
  assign _02_ = rst ? 19'h00000 : p0;
  assign _15_ = rst ? 1'h0 : in_valid;
  assign _16_ = in_valid ? t4 : t5;
  assign _13_ = rst ? 8'h00 : _16_;
  assign _17_ = in_valid ? t3 : t4;
  assign _12_ = rst ? 8'h00 : _17_;
  assign _18_ = in_valid ? t2 : t3;
  assign _11_ = rst ? 8'h00 : _18_;
  assign _19_ = in_valid ? t1 : t2;
  assign _10_ = rst ? 8'h00 : _19_;
  assign _20_ = in_valid ? t0 : t1;
  assign _09_ = rst ? 8'h00 : _20_;
  assign _21_ = in_valid ? in_data : t0;
  assign _08_ = rst ? 8'h00 : _21_;
endmodule

module gold(clk, rst, in_valid, in_data, out_valid, out_data);
  input clk;
  wire clk;
  input rst;
  wire rst;
  input in_valid;
  wire in_valid;
  input signed [7:0] in_data;
  wire signed [7:0] in_data;
  output out_valid;
  reg out_valid;
  output signed [18:0] out_data;
  reg signed [18:0] out_data;
  wire [18:0] _00_;
  wire _01_;
  wire [7:0] _02_;
  wire [7:0] _03_;
  wire [7:0] _04_;
  wire [7:0] _05_;
  wire [7:0] _06_;
  wire [7:0] _07_;
  wire _08_;
  wire [7:0] _09_;
  wire [7:0] _10_;
  wire [7:0] _11_;
  wire [7:0] _12_;
  wire [7:0] _13_;
  wire [7:0] _14_;
  wire signed [18:0] p0;
  wire signed [18:0] p1;
  wire signed [18:0] p2;
  wire signed [18:0] p3;
  wire signed [18:0] p4;
  wire signed [18:0] p5;
  wire signed [18:0] s1;
  wire signed [18:0] s2;
  wire signed [18:0] s3;
  wire signed [18:0] s4;
  wire signed [18:0] s5;
  reg signed [7:0] t0;
  reg signed [7:0] t1;
  reg signed [7:0] t2;
  reg signed [7:0] t3;
  reg signed [7:0] t4;
  reg signed [7:0] t5;
  reg vld;
  assign s1 = $signed(p0) + $signed(p1);
  assign s2 = $signed(s1) + $signed(p2);
  assign s3 = $signed(s2) + $signed(p3);
  assign s4 = $signed(s3) + $signed(p4);
  assign s5 = $signed(s4) + $signed(p5);
  assign p0 = $signed(t0) * $signed(8'h17);
  assign p1 = $signed(t1) * $signed(8'hd1);
  assign p2 = $signed(t2) * $signed(8'h51);
  assign p3 = $signed(t3) * $signed(8'h51);
  assign p4 = $signed(t4) * $signed(8'hd1);
  assign p5 = $signed(t5) * $signed(8'h17);
  always @(posedge clk)
    out_valid <= _01_;
  always @(posedge clk)
    out_data <= _00_;
  always @(posedge clk)
    vld <= _08_;
  always @(posedge clk)
    t0 <= _02_;
  always @(posedge clk)
    t1 <= _03_;
  always @(posedge clk)
    t2 <= _04_;
  always @(posedge clk)
    t3 <= _05_;
  always @(posedge clk)
    t4 <= _06_;
  always @(posedge clk)
    t5 <= _07_;
  assign _01_ = rst ? 1'h0 : vld;
  assign _00_ = rst ? 19'h00000 : s5;
  assign _08_ = rst ? 1'h0 : in_valid;
  assign _09_ = in_valid ? t4 : t5;
  assign _07_ = rst ? 8'h00 : _09_;
  assign _10_ = in_valid ? t3 : t4;
  assign _06_ = rst ? 8'h00 : _10_;
  assign _11_ = in_valid ? t2 : t3;
  assign _05_ = rst ? 8'h00 : _11_;
  assign _12_ = in_valid ? t1 : t2;
  assign _04_ = rst ? 8'h00 : _12_;
  assign _13_ = in_valid ? t0 : t1;
  assign _03_ = rst ? 8'h00 : _13_;
  assign _14_ = in_valid ? in_data : t0;
  assign _02_ = rst ? 8'h00 : _14_;
endmodule

runs/web_b5258d7e4ad0_optimize_20260914T144523Z/round_3/attempt_1/candidate_1/formal/equiv_prove/src/eqcheck_wrapper.v
module __eqcheck_top (
    input wire clk,
    input wire rst,
    input wire in_valid,
    input wire [7:0] in_data
);

    wire gold_out_valid;
    wire gate_out_valid;
    wire [18:0] gold_out_data;
    wire [18:0] gate_out_data;

    gold gold_inst (
        .clk(clk),
        .rst(rst),
        .in_valid(in_valid),
        .in_data(in_data),
        .out_valid(gold_out_valid),
        .out_data(gold_out_data)
    );

    gate gate_inst (
        .clk(clk),
        .rst(rst),
        .in_valid(in_valid),
        .in_data(in_data),
        .out_valid(gate_out_valid),
        .out_data(gate_out_data)
    );

    // Latency offset of 1 cycle(s): the candidate produces its
    // outputs later than the baseline (added pipeline stages), so the baseline's
    // outputs are delayed by that many cycles before being compared.
    reg gold_out_valid_d1;
    reg [18:0] gold_out_data_d1;

    always @(posedge clk) begin
        gold_out_valid_d1 <= gold_out_valid;
        gold_out_data_d1 <= gold_out_data;
    end

    // Comparison is suppressed until the delay pipeline has filled.
    reg [7:0] warmup = 8'd0;
    always @(posedge clk) begin
        if (rst) warmup <= 8'd0;
        else if (warmup < 8'd1) warmup <= warmup + 8'd1;
    end

    // First cycle: force a real reset via $initstate before comparing,
    // so the proof isn't defeated by unconstrained initial register state.
    always @(posedge clk) begin
        if ($initstate) begin
            assume (rst);
        end else begin
            if (warmup >= 8'd1) assert (gold_out_valid_d1 == gate_out_valid && gold_out_data_d1 == gate_out_data);
        end
    end

endmodule

runs/web_b5258d7e4ad0_optimize_20260914T144523Z/round_3/attempt_2/candidate_1/formal/equiv_prove/engine_0/trace_induct.vcd
$version Generated by Yosys-SMTBMC $end
$timescale 1ns $end
$var integer 32 t smt_step $end
$var event 1 ! smt_clock $end
$scope module __eqcheck_top $end
$var wire 1 n0 clk $end
$scope module gate_inst $end
$var wire 19 n1 _00_ $end
$var wire 1 n2 _01_ $end
$var wire 19 n3 _02_ $end
$var wire 19 n4 _03_ $end
$var wire 19 n5 _04_ $end
$var wire 19 n6 _05_ $end
$var wire 19 n7 _06_ $end
$var wire 19 n8 _07_ $end
$var wire 8 n9 _08_ $end
$var wire 8 n10 _09_ $end
$var wire 8 n11 _10_ $end
$var wire 8 n12 _11_ $end
$var wire 8 n13 _12_ $end
$var wire 8 n14 _13_ $end
$var wire 1 n15 _14_ $end
$var wire 1 n16 _15_ $end
$var wire 8 n17 _16_ $end
$var wire 8 n18 _17_ $end
$var wire 8 n19 _18_ $end
$var wire 8 n20 _19_ $end
$var wire 8 n21 _20_ $end
$var wire 8 n22 _21_ $end
$var wire 1 n23 clk $end
$var wire 8 n24 in_data $end
$var wire 1 n25 in_valid $end
$var wire 19 n26 out_data $end
$var wire 1 n27 out_valid $end
$var wire 19 n28 p0 $end
$var wire 19 n29 p0_r $end
$var wire 19 n30 p1 $end
$var wire 19 n31 p1_r $end
$var wire 19 n32 p2 $end
$var wire 19 n33 p2_r $end
$var wire 19 n34 p3 $end
$var wire 19 n35 p3_r $end
$var wire 19 n36 p4 $end
$var wire 19 n37 p4_r $end
$var wire 19 n38 p5 $end
$var wire 19 n39 p5_r $end
$var wire 1 n40 rst $end
$var wire 19 n41 s1 $end
$var wire 19 n42 s2 $end
$var wire 19 n43 s3 $end
$var wire 19 n44 s4 $end
$var wire 19 n45 s5 $end
$var wire 8 n46 t0 $end
$var wire 8 n47 t1 $end
$var wire 8 n48 t2 $end
$var wire 8 n49 t3 $end
$var wire 8 n50 t4 $end
$var wire 8 n51 t5 $end
$var wire 1 n52 vld $end
$var wire 1 n53 vld2 $end
$upscope $end
$var wire 19 n54 gate_out_data $end
$var wire 1 n55 gate_out_valid $end
$scope module gold_inst $end
$var wire 19 n56 _00_ $end
$var wire 1 n57 _01_ $end
$var wire 8 n58 _02_ $end
$var wire 8 n59 _03_ $end
$var wire 8 n60 _04_ $end
$var wire 8 n61 _05_ $end
$var wire 8 n62 _06_ $end
$var wire 8 n63 _07_ $end
$var wire 1 n64 _08_ $end
$var wire 8 n65 _09_ $end
$var wire 8 n66 _10_ $end
$var wire 8 n67 _11_ $end
$var wire 8 n68 _12_ $end
$var wire 8 n69 _13_ $end
$var wire 8 n70 _14_ $end
$var wire 1 n71 clk $end
$var wire 8 n72 in_data $end
$var wire 1 n73 in_valid $end
$var wire 19 n74 out_data $end
$var wire 1 n75 out_valid $end
$var wire 19 n76 p0 $end
$var wire 19 n77 p1 $end
$var wire 19 n78 p2 $end
$var wire 19 n79 p3 $end
$var wire 19 n80 p4 $end
$var wire 19 n81 p5 $end
$var wire 1 n82 rst $end
$var wire 19 n83 s1 $end
$var wire 19 n84 s2 $end
$var wire 19 n85 s3 $end
$var wire 19 n86 s4 $end
$var wire 19 n87 s5 $end
$var wire 8 n88 t0 $end
$var wire 8 n89 t1 $end
$var wire 8 n90 t2 $end
$var wire 8 n91 t3 $end
$var wire 8 n92 t4 $end
$var wire 8 n93 t5 $end
$var wire 1 n94 vld $end
$upscope $end
$var wire 19 n95 gold_out_data $end
$var wire 19 n96 gold_out_data_d1 $end
$var wire 1 n97 gold_out_valid $end
$var wire 1 n98 gold_out_valid_d1 $end
$var wire 8 n99 in_data $end
$var wire 1 n100 in_valid $end
$var wire 1 n101 rst $end
$var wire 8 n102 warmup $end
$upscope $end
$enddefinitions $end
#0
1!
b00000000000000000000000000000000 t
b1 n0
b1 n23
b1 n71
b0000000000000000000 n1
b0 n2
b0000000011110001100 n3
b1111111000011000011 n4
b1111101011111010001 n5
b0000001111001100000 n6
b0000000100011111111 n7
b0000000010111000000 n8
b01010100 n9
b01010011 n10
b10000001 n11
b01100000 n12
b11001111 n13
b01000000 n14
b0 n15
b0 n16
b01000000 n17
b11001111 n18
b01100000 n19
b10000001 n20
b01010011 n21
b01010100 n22
b00000000 n24
b0 n25
b0000000000000000000 n26
b0 n27
b0000000011110001100 n28
b0000000000000000000 n29
b1111111000011000011 n30
b0000000000000000000 n31
b1111101011111010001 n32
b0000000000000000000 n33
b0000001111001100000 n34
b0000000000000000000 n35
b0000000100011111111 n36
b0000000000000000000 n37
b0000000010111000000 n38
b0000000000000000000 n39
b0 n40
b0000000000000000000 n41
b0000000000000000000 n42
b0000000000000000000 n43
b0000000000000000000 n44
b0000000000000000000 n45
b01010100 n46
b01010011 n47
b10000001 n48
b01100000 n49
b11001111 n50
b01000000 n51
b0 n52
b0 n53
b0000000000000000000 n54
b0 n55
b1111111110100111111 n56
b0 n57
b01111010 n58
b10111000 n59
b10000100 n60
b11111101 n61
b10000010 n62
b10010010 n63
b0 n64
b10010010 n65
b10000010 n66
b11111101 n67
b10000100 n68
b10111000 n69
b01111010 n70
b00000000 n72
b0 n73
b0000000000000000000 n74
b0 n75
b0000000101011110110 n76
b0000000110100111000 n77
b1111101100011000100 n78
b1111111111100001101 n79
b0000001011100100010 n80
b1111111011000011110 n81
b0 n82
b0000001100000101110 n83
b1111111000011110010 n84
b1111110111111111111 n85
b0000000011100100001 n86
b1111111110100111111 n87
b01111010 n88
b10111000 n89
b10000100 n90
b11111101 n91
b10000010 n92
b10010010 n93
b0 n94
b0000000000000000000 n95
b0000000000000000000 n96
b0 n97
b0 n98
b00000000 n99
b0 n100
b0 n101
b00010010 n102
#5
b0 n0
b0 n23
b0 n71
#10
1!
b00000000000000000000000000000001 t
b1 n0
b1 n23
b1 n71
b1111111110100111111 n1
b0 n2
b0000000011110001100 n3
b1111111000011000011 n4
b1111101011111010001 n5
b0000001111001100000 n6
b0000000100011111111 n7
b0000000010111000000 n8
b01010100 n9
b01010011 n10
b10000001 n11
b01100000 n12
b11001111 n13
b01000000 n14
b0 n15
b0 n16
b01000000 n17
b11001111 n18
b01100000 n19
b10000001 n20
b01010011 n21
b01010100 n22
b00000000 n24
b0 n25
b0000000000000000000 n26
b0 n27
b0000000011110001100 n28
b0000000011110001100 n29
b1111111000011000011 n30
b1111111000011000011 n31
b1111101011111010001 n32
b1111101011111010001 n33
b0000001111001100000 n34
b0000001111001100000 n35
b0000000100011111111 n36
b0000000100011111111 n37
b0000000010111000000 n38
b0000000010111000000 n39
b0 n40
b1111111100001001111 n41
b1111101000000100000 n42
b1111110111010000000 n43
b1111111011101111111 n44
b1111111110100111111 n45
b01010100 n46
b01010011 n47
b10000001 n48
b01100000 n49
b11001111 n50
b01000000 n51
b0 n52
b0 n53
b0000000000000000000 n54
b0 n55
b1111111110100111111 n56
b0 n57
b01111010 n58
b10111000 n59
b10000100 n60
b11111101 n61
b10000010 n62
b10010010 n63
b0 n64
b10010010 n65
b10000010 n66
b11111101 n67
b10000100 n68
b10111000 n69
b01111010 n70
b00000000 n72
b0 n73
b1111111110100111111 n74
b0 n75
b0000000101011110110 n76
b0000000110100111000 n77
b1111101100011000100 n78
b1111111111100001101 n79
b0000001011100100010 n80
b1111111011000011110 n81
b0 n82
b0000001100000101110 n83
b1111111000011110010 n84
b1111110111111111111 n85
b0000000011100100001 n86
b1111111110100111111 n87
b01111010 n88
b10111000 n89
b10000100 n90
b11111101 n91
b10000010 n92
b10010010 n93
b0 n94
b1111111110100111111 n95
b0000000000000000000 n96
b0 n97
b0 n98
b00000000 n99
b0 n100
b0 n101
b00010010 n102
#15
b0 n0
b0 n23
b0 n71
#20
1!
b00000000000000000000000000000010 t
b1 n0
b1 n23
b1 n71
b1111111110100111111 n1
b0 n2
b0000000011110001100 n3
b1111111000011000011 n4
b1111101011111010001 n5
b0000001111001100000 n6
b0000000100011111111 n7
b0000000010111000000 n8
b01010100 n9
b01010011 n10
b10000001 n11
b01100000 n12
b11001111 n13
b01000000 n14
b0 n15
b0 n16
b01000000 n17
b11001111 n18
b01100000 n19
b10000001 n20
b01010011 n21
b01010100 n22
b00000000 n24
b0 n25
b1111111110100111111 n26
b0 n27
b0000000011110001100 n28
b0000000011110001100 n29
b1111111000011000011 n30
b1111111000011000011 n31
b1111101011111010001 n32
b1111101011111010001 n33
b0000001111001100000 n34
b0000001111001100000 n35
b0000000100011111111 n36
b0000000100011111111 n37
b0000000010111000000 n38
b0000000010111000000 n39
b0 n40
b1111111100001001111 n41
b1111101000000100000 n42
b1111110111010000000 n43
b1111111011101111111 n44
b1111111110100111111 n45
b01010100 n46
b01010011 n47
b10000001 n48
b01100000 n49
b11001111 n50
b01000000 n51
b0 n52
b0 n53
b1111111110100111111 n54
b0 n55
b1111111110100111111 n56
b0 n57
b01111010 n58
b10111000 n59
b10000100 n60
b11111101 n61
b10000010 n62
b10010010 n63
b0 n64
b10010010 n65
b10000010 n66
b11111101 n67
b10000100 n68
b10111000 n69
b01111010 n70
b00000000 n72
b0 n73
b1111111110100111111 n74
b0 n75
b0000000101011110110 n76
b0000000110100111000 n77
b1111101100011000100 n78
b1111111111100001101 n79
b0000001011100100010 n80
b1111111011000011110 n81
b0 n82
b0000001100000101110 n83
b1111111000011110010 n84
b1111110111111111111 n85
b0000000011100100001 n86
b1111111110100111111 n87
b01111010 n88
b10111000 n89
b10000100 n90
b11111101 n91
b10000010 n92
b10010010 n93
b0 n94
b1111111110100111111 n95
b1111111110100111111 n96
b0 n97
b0 n98
b00000000 n99
b0 n100
b0 n101
b00010010 n102
#25
b0 n0
b0 n23
b0 n71
#30
1!
b00000000000000000000000000000011 t
b1 n0
b1 n23
b1 n71
b1111111110100111111 n1
b0 n2
b0000000011110001100 n3
b1111111000011000011 n4
b1111101011111010001 n5
b0000001111001100000 n6
b0000000100011111111 n7
b0000000010111000000 n8
b01010100 n9
b01010011 n10
b10000001 n11
b01100000 n12
b11001111 n13
b01000000 n14
b0 n15
b0 n16
b01000000 n17
b11001111 n18
b01100000 n19
b10000001 n20
b01010011 n21
b01010100 n22
b00000000 n24
b0 n25
b1111111110100111111 n26
b0 n27
b0000000011110001100 n28
b0000000011110001100 n29
b1111111000011000011 n30
b1111111000011000011 n31
b1111101011111010001 n32
b1111101011111010001 n33
b0000001111001100000 n34
b0000001111001100000 n35
b0000000100011111111 n36
b0000000100011111111 n37
b0000000010111000000 n38
b0000000010111000000 n39
b0 n40
b1111111100001001111 n41
b1111101000000100000 n42
b1111110111010000000 n43
b1111111011101111111 n44
b1111111110100111111 n45
b01010100 n46
b01010011 n47
b10000001 n48
b01100000 n49
b11001111 n50
b01000000 n51
b0 n52
b0 n53
b1111111110100111111 n54
b0 n55
b1111111110100111111 n56
b0 n57
b01111010 n58
b10111000 n59
b10000100 n60
b11111101 n61
b10000010 n62
b10010010 n63
b0 n64
b10010010 n65
b10000010 n66
b11111101 n67
b10000100 n68
b10111000 n69
b01111010 n70
b00000000 n72
b0 n73
b1111111110100111111 n74
b0 n75
b0000000101011110110 n76
b0000000110100111000 n77
b1111101100011000100 n78
b1111111111100001101 n79
b0000001011100100010 n80
b1111111011000011110 n81
b0 n82
b0000001100000101110 n83
b1111111000011110010 n84
b1111110111111111111 n85
b0000000011100100001 n86
b1111111110100111111 n87
b01111010 n88
b10111000 n89
b10000100 n90
b11111101 n91
b10000010 n92
b10010010 n93
b0 n94
b1111111110100111111 n95
b1111111110100111111 n96
b0 n97
b0 n98
b00000000 n99
b0 n100
b0 n101
b00010010 n102
#35
b0 n0
b0 n23
b0 n71
#40
1!
b00000000000000000000000000000100 t
b1 n0
b1 n23
b1 n71
b1111111110100111111 n1
b0 n2
b0000000011110001100 n3
b1111111000011000011 n4
b1111101011111010001 n5
b0000001111001100000 n6
b0000000100011111111 n7
b0000000010111000000 n8
b01010100 n9
b01010011 n10
b10000001 n11
b01100000 n12
b11001111 n13
b01000000 n14
b0 n15
b0 n16
b01000000 n17
b11001111 n18
b01100000 n19
b10000001 n20
b01010011 n21
b01010100 n22
b00000000 n24
b0 n25
b1111111110100111111 n26
b0 n27
b0000000011110001100 n28
b0000000011110001100 n29
b1111111000011000011 n30
b1111111000011000011 n31
b1111101011111010001 n32
b1111101011111010001 n33
b0000001111001100000 n34
b0000001111001100000 n35
b0000000100011111111 n36
b0000000100011111111 n37
b0000000010111000000 n38
b0000000010111000000 n39
b0 n40
b1111111100001001111 n41
b1111101000000100000 n42
b1111110111010000000 n43
b1111111011101111111 n44
b1111111110100111111 n45
b01010100 n46
b01010011 n47
b10000001 n48
b01100000 n49
b11001111 n50
b01000000 n51
b0 n52
b0 n53
b1111111110100111111 n54
b0 n55
b1111111110100111111 n56
b0 n57
b01111010 n58
b10111000 n59
b10000100 n60
b11111101 n61
b10000010 n62
b10010010 n63
b0 n64
b10010010 n65
b10000010 n66
b11111101 n67
b10000100 n68
b10111000 n69
b01111010 n70
b00000000 n72
b0 n73
b1111111110100111111 n74
b0 n75
b0000000101011110110 n76
b0000000110100111000 n77
b1111101100011000100 n78
b1111111111100001101 n79
b0000001011100100010 n80
b1111111011000011110 n81
b0 n82
b0000001100000101110 n83
b1111111000011110010 n84
b1111110111111111111 n85
b0000000011100100001 n86
b1111111110100111111 n87
b01111010 n88
b10111000 n89
b10000100 n90
b11111101 n91
b10000010 n92
b10010010 n93
b0 n94
b1111111110100111111 n95
b1111111110100111111 n96
b0 n97
b0 n98
b00000000 n99
b0 n100
b0 n101
b00010010 n102
#45
b0 n0
b0 n23
b0 n71
#50
1!
b00000000000000000000000000000101 t
b1 n0
b1 n23
b1 n71
b1111111110100111111 n1
b0 n2
b0000000011110001100 n3
b1111111000011000011 n4
b1111101011111010001 n5
b0000001111001100000 n6
b0000000100011111111 n7
b0000000010111000000 n8
b01010100 n9
b01010011 n10
b10000001 n11
b01100000 n12
b11001111 n13
b01000000 n14
b0 n15
b0 n16
b01000000 n17
b11001111 n18
b01100000 n19
b10000001 n20
b01010011 n21
b01010100 n22
b00000000 n24
b0 n25
b1111111110100111111 n26
b0 n27
b0000000011110001100 n28
b0000000011110001100 n29
b1111111000011000011 n30
b1111111000011000011 n31
b1111101011111010001 n32
b1111101011111010001 n33
b0000001111001100000 n34
b0000001111001100000 n35
b0000000100011111111 n36
b0000000100011111111 n37
b0000000010111000000 n38
b0000000010111000000 n39
b0 n40
b1111111100001001111 n41
b1111101000000100000 n42
b1111110111010000000 n43
b1111111011101111111 n44
b1111111110100111111 n45
b01010100 n46
b01010011 n47
b10000001 n48
b01100000 n49
b11001111 n50
b01000000 n51
b0 n52
b0 n53
b1111111110100111111 n54
b0 n55
b1111111110100111111 n56
b0 n57
b01111010 n58
b10111000 n59
b10000100 n60
b11111101 n61
b10000010 n62
b10010010 n63
b0 n64
b10010010 n65
b10000010 n66
b11111101 n67
b10000100 n68
b10111000 n69
b01111010 n70
b00000000 n72
b0 n73
b1111111110100111111 n74
b0 n75
b0000000101011110110 n76
b0000000110100111000 n77
b1111101100011000100 n78
b1111111111100001101 n79
b0000001011100100010 n80
b1111111011000011110 n81
b0 n82
b0000001100000101110 n83
b1111111000011110010 n84
b1111110111111111111 n85
b0000000011100100001 n86
b1111111110100111111 n87
b01111010 n88
b10111000 n89
b10000100 n90
b11111101 n91
b10000010 n92
b10010010 n93
b0 n94
b1111111110100111111 n95
b1111111110100111111 n96
b0 n97
b0 n98
b00000000 n99
b0 n100
b0 n101
b00010010 n102
#55
b0 n0
b0 n23
b0 n71
#60
1!
b00000000000000000000000000000110 t
b1 n0
b1 n23
b1 n71
b1111111110100111111 n1
b0 n2
b0000000011110001100 n3
b1111111000011000011 n4
b1111101011111010001 n5
b0000001111001100000 n6
b0000000100011111111 n7
b0000000010111000000 n8
b01010100 n9
b01010011 n10
b10000001 n11
b01100000 n12
b11001111 n13
b01000000 n14
b0 n15
b0 n16
b01000000 n17
b11001111 n18
b01100000 n19
b10000001 n20
b01010011 n21
b01010100 n22
b00000000 n24
b0 n25
b1111111110100111111 n26
b0 n27
b0000000011110001100 n28
b0000000011110001100 n29
b1111111000011000011 n30
b1111111000011000011 n31
b1111101011111010001 n32
b1111101011111010001 n33
b0000001111001100000 n34
b0000001111001100000 n35
b0000000100011111111 n36
b0000000100011111111 n37
b0000000010111000000 n38
b0000000010111000000 n39
b0 n40
b1111111100001001111 n41
b1111101000000100000 n42
b1111110111010000000 n43
b1111111011101111111 n44
b1111111110100111111 n45
b01010100 n46
b01010011 n47
b10000001 n48
b01100000 n49
b11001111 n50
b01000000 n51
b0 n52
b0 n53
b1111111110100111111 n54
b0 n55
b1111111110100111111 n56
b0 n57
b01111010 n58
b10111000 n59
b10000100 n60
b11111101 n61
b10000010 n62
b10010010 n63
b0 n64
b10010010 n65
b10000010 n66
b11111101 n67
b10000100 n68
b10111000 n69
b01111010 n70
b00000000 n72
b0 n73
b1111111110100111111 n74
b0 n75
b0000000101011110110 n76
b0000000110100111000 n77
b1111101100011000100 n78
b1111111111100001101 n79
b0000001011100100010 n80
b1111111011000011110 n81
b0 n82
b0000001100000101110 n83
b1111111000011110010 n84
b1111110111111111111 n85
b0000000011100100001 n86
b1111111110100111111 n87
b01111010 n88
b10111000 n89
b10000100 n90
b11111101 n91
b10000010 n92
b10010010 n93
b0 n94
b1111111110100111111 n95
b1111111110100111111 n96
b0 n97
b0 n98
b00000000 n99
b0 n100
b0 n101
b00010010 n102
#65
b0 n0
b0 n23
b0 n71
#70
1!
b00000000000000000000000000000111 t
b1 n0
b1 n23
b1 n71
b1111111110100111111 n1
b0 n2
b0000000011110001100 n3
b1111111000011000011 n4
b1111101011111010001 n5
b0000001111001100000 n6
b0000000100011111111 n7
b0000000010111000000 n8
b01010100 n9
b01010011 n10
b10000001 n11
b01100000 n12
b11001111 n13
b01000000 n14
b0 n15
b0 n16
b01000000 n17
b11001111 n18
b01100000 n19
b10000001 n20
b01010011 n21
b01010100 n22
b00000000 n24
b0 n25
b1111111110100111111 n26
b0 n27
b0000000011110001100 n28
b0000000011110001100 n29
b1111111000011000011 n30
b1111111000011000011 n31
b1111101011111010001 n32
b1111101011111010001 n33
b0000001111001100000 n34
b0000001111001100000 n35
b0000000100011111111 n36
b0000000100011111111 n37
b0000000010111000000 n38
b0000000010111000000 n39
b0 n40
b1111111100001001111 n41
b1111101000000100000 n42
b1111110111010000000 n43
b1111111011101111111 n44
b1111111110100111111 n45
b01010100 n46
b01010011 n47
b10000001 n48
b01100000 n49
b11001111 n50
b01000000 n51
b0 n52
b0 n53
b1111111110100111111 n54
b0 n55
b1111111110100111111 n56
b0 n57
b01111010 n58
b10111000 n59
b10000100 n60
b11111101 n61
b10000010 n62
b10010010 n63
b0 n64
b10010010 n65
b10000010 n66
b11111101 n67
b10000100 n68
b10111000 n69
b01111010 n70
b00000000 n72
b0 n73
b1111111110100111111 n74
b0 n75
b0000000101011110110 n76
b0000000110100111000 n77
b1111101100011000100 n78
b1111111111100001101 n79
b0000001011100100010 n80
b1111111011000011110 n81
b0 n82
b0000001100000101110 n83
b1111111000011110010 n84
b1111110111111111111 n85
b0000000011100100001 n86
b1111111110100111111 n87
b01111010 n88
b10111000 n89
b10000100 n90
b11111101 n91
b10000010 n92
b10010010 n93
b0 n94
b1111111110100111111 n95
b1111111110100111111 n96
b0 n97
b0 n98
b00000000 n99
b0 n100
b0 n101
b00010010 n102
#75
b0 n0
b0 n23
b0 n71
#80
1!
b00000000000000000000000000001000 t
b1 n0
b1 n23
b1 n71
b1111111110100111111 n1
b0 n2
b0000000011110001100 n3
b1111111000011000011 n4
b1111101011111010001 n5
b0000001111001100000 n6
b0000000100011111111 n7
b0000000010111000000 n8
b01010100 n9
b01010011 n10
b10000001 n11
b01100000 n12
b11001111 n13
b01000000 n14
b0 n15
b0 n16
b01000000 n17
b11001111 n18
b01100000 n19
b10000001 n20
b01010011 n21
b01010100 n22
b00000000 n24
b0 n25
b1111111110100111111 n26
b0 n27
b0000000011110001100 n28
b0000000011110001100 n29
b1111111000011000011 n30
b1111111000011000011 n31
b1111101011111010001 n32
b1111101011111010001 n33
b0000001111001100000 n34
b0000001111001100000 n35
b0000000100011111111 n36
b0000000100011111111 n37
b0000000010111000000 n38
b0000000010111000000 n39
b0 n40
b1111111100001001111 n41
b1111101000000100000 n42
b1111110111010000000 n43
b1111111011101111111 n44
b1111111110100111111 n45
b01010100 n46
b01010011 n47
b10000001 n48
b01100000 n49
b11001111 n50
b01000000 n51
b0 n52
b0 n53
b1111111110100111111 n54
b0 n55
b1111111110100111111 n56
b0 n57
b01111010 n58
b10111000 n59
b10000100 n60
b11111101 n61
b10000010 n62
b10010010 n63
b0 n64
b10010010 n65
b10000010 n66
b11111101 n67
b10000100 n68
b10111000 n69
b01111010 n70
b00000000 n72
b0 n73
b1111111110100111111 n74
b0 n75
b0000000101011110110 n76
b0000000110100111000 n77
b1111101100011000100 n78
b1111111111100001101 n79
b0000001011100100010 n80
b1111111011000011110 n81
b0 n82
b0000001100000101110 n83
b1111111000011110010 n84
b1111110111111111111 n85
b0000000011100100001 n86
b1111111110100111111 n87
b01111010 n88
b10111000 n89
b10000100 n90
b11111101 n91
b10000010 n92
b10010010 n93
b0 n94
b1111111110100111111 n95
b1111111110100111111 n96
b0 n97
b0 n98
b00000000 n99
b0 n100
b0 n101
b00010010 n102
