runs/web_f6e793600ee7_optimize_20260915T134737Z/round_3/attempt_1/candidate_1/formal/equiv_prove/src/gold_gate.v
/* Generated by Yosys 0.68+195 (git sha1 435977e97-dirty, Release, Clang /usr/bin/clang++ 21.1.8) */

module gate(clk, rst, in_valid, in_data, out_valid, out_data);
  input clk;
  wire clk;
  input rst;
  wire rst;
  input in_valid;
  wire in_valid;
  input signed [7:0] in_data;
  wire signed [7:0] in_data;
  output out_valid;
  reg out_valid;
  output signed [18:0] out_data;
  reg signed [18:0] out_data;
  wire [18:0] _00_;
  wire _01_;
  wire [7:0] _02_;
  wire [7:0] _03_;
  wire [7:0] _04_;
  wire [7:0] _05_;
  wire [7:0] _06_;
  wire [7:0] _07_;
  wire _08_;
  wire [7:0] _09_;
  wire [7:0] _10_;
  wire [7:0] _11_;
  wire [7:0] _12_;
  wire [7:0] _13_;
  wire [7:0] _14_;
  wire signed [18:0] p0;
  wire signed [18:0] p1;
  wire signed [18:0] p2;
  wire signed [18:0] p3;
  wire signed [18:0] p4;
  wire signed [18:0] p5;
  wire signed [18:0] s1;
  wire signed [18:0] s2;
  wire signed [18:0] s3;
  wire signed [18:0] s4;
  wire signed [18:0] s5;
  reg signed [7:0] t0;
  reg signed [7:0] t1;
  reg signed [7:0] t2;
  reg signed [7:0] t3;
  reg signed [7:0] t4;
  reg signed [7:0] t5;
  reg vld;
  assign s1 = $signed(p0) + $signed(p1);
  assign s2 = $signed(p2) + $signed(p3);
  assign s3 = $signed(p4) + $signed(p5);
  assign s4 = $signed(s1) + $signed(s2);
  assign s5 = $signed(s4) + $signed(s3);
  assign p0 = $signed(t0) * $signed(8'h17);
  assign p1 = $signed(t1) * $signed(8'hd1);
  assign p2 = $signed(t2) * $signed(8'h51);
  assign p3 = $signed(t3) * $signed(8'h51);
  assign p4 = $signed(t4) * $signed(8'hd1);
  assign p5 = $signed(t5) * $signed(8'h17);
  always @(posedge clk)
    out_valid <= _01_;
  always @(posedge clk)
    out_data <= _00_;
  always @(posedge clk)
    vld <= _08_;
  always @(posedge clk)
    t0 <= _02_;
  always @(posedge clk)
    t1 <= _03_;
  always @(posedge clk)
    t2 <= _04_;
  always @(posedge clk)
    t3 <= _05_;
  always @(posedge clk)
    t4 <= _06_;
  always @(posedge clk)
    t5 <= _07_;
  assign _01_ = rst ? 1'h0 : vld;
  assign _00_ = rst ? 19'h00000 : s5;
  assign _08_ = rst ? 1'h0 : in_valid;
  assign _09_ = in_valid ? t4 : t5;
  assign _07_ = rst ? 8'h00 : _09_;
  assign _10_ = in_valid ? t3 : t4;
  assign _06_ = rst ? 8'h00 : _10_;
  assign _11_ = in_valid ? t2 : t3;
  assign _05_ = rst ? 8'h00 : _11_;
  assign _12_ = in_valid ? t1 : t2;
  assign _04_ = rst ? 8'h00 : _12_;
  assign _13_ = in_valid ? t0 : t1;
  assign _03_ = rst ? 8'h00 : _13_;
  assign _14_ = in_valid ? in_data : t0;
  assign _02_ = rst ? 8'h00 : _14_;
endmodule

module gold(clk, rst, in_valid, in_data, out_valid, out_data);
  input clk;
  wire clk;
  input rst;
  wire rst;
  input in_valid;
  wire in_valid;
  input signed [7:0] in_data;
  wire signed [7:0] in_data;
  output out_valid;
  reg out_valid;
  output signed [18:0] out_data;
  reg signed [18:0] out_data;
  wire [18:0] _00_;
  wire _01_;
  wire [7:0] _02_;
  wire [7:0] _03_;
  wire [7:0] _04_;
  wire [7:0] _05_;
  wire [7:0] _06_;
  wire [7:0] _07_;
  wire _08_;
  wire [7:0] _09_;
  wire [7:0] _10_;
  wire [7:0] _11_;
  wire [7:0] _12_;
  wire [7:0] _13_;
  wire [7:0] _14_;
  wire signed [18:0] p0;
  wire signed [18:0] p1;
  wire signed [18:0] p2;
  wire signed [18:0] p3;
  wire signed [18:0] p4;
  wire signed [18:0] p5;
  wire signed [18:0] s1;
  wire signed [18:0] s2;
  wire signed [18:0] s3;
  wire signed [18:0] s4;
  wire signed [18:0] s5;
  reg signed [7:0] t0;
  reg signed [7:0] t1;
  reg signed [7:0] t2;
  reg signed [7:0] t3;
  reg signed [7:0] t4;
  reg signed [7:0] t5;
  reg vld;
  assign s1 = $signed(p0) + $signed(p1);
  assign s2 = $signed(s1) + $signed(p2);
  assign s3 = $signed(s2) + $signed(p3);
  assign s4 = $signed(s3) + $signed(p4);
  assign s5 = $signed(s4) + $signed(p5);
  assign p0 = $signed(t0) * $signed(8'h17);
  assign p1 = $signed(t1) * $signed(8'hd1);
  assign p2 = $signed(t2) * $signed(8'h51);
  assign p3 = $signed(t3) * $signed(8'h51);
  assign p4 = $signed(t4) * $signed(8'hd1);
  assign p5 = $signed(t5) * $signed(8'h17);
  always @(posedge clk)
    out_valid <= _01_;
  always @(posedge clk)
    out_data <= _00_;
  always @(posedge clk)
    vld <= _08_;
  always @(posedge clk)
    t0 <= _02_;
  always @(posedge clk)
    t1 <= _03_;
  always @(posedge clk)
    t2 <= _04_;
  always @(posedge clk)
    t3 <= _05_;
  always @(posedge clk)
    t4 <= _06_;
  always @(posedge clk)
    t5 <= _07_;
  assign _01_ = rst ? 1'h0 : vld;
  assign _00_ = rst ? 19'h00000 : s5;
  assign _08_ = rst ? 1'h0 : in_valid;
  assign _09_ = in_valid ? t4 : t5;
  assign _07_ = rst ? 8'h00 : _09_;
  assign _10_ = in_valid ? t3 : t4;
  assign _06_ = rst ? 8'h00 : _10_;
  assign _11_ = in_valid ? t2 : t3;
  assign _05_ = rst ? 8'h00 : _11_;
  assign _12_ = in_valid ? t1 : t2;
  assign _04_ = rst ? 8'h00 : _12_;
  assign _13_ = in_valid ? t0 : t1;
  assign _03_ = rst ? 8'h00 : _13_;
  assign _14_ = in_valid ? in_data : t0;
  assign _02_ = rst ? 8'h00 : _14_;
endmodule

runs/web_f6e793600ee7_optimize_20260915T134737Z/round_3/attempt_1/candidate_1/formal/equiv_bmc/src/eqcheck_wrapper.v
module __eqcheck_top (
    input wire clk,
    input wire rst,
    input wire in_valid,
    input wire [7:0] in_data
);

    wire gold_out_valid;
    wire gate_out_valid;
    wire [18:0] gold_out_data;
    wire [18:0] gate_out_data;

    gold gold_inst (
        .clk(clk),
        .rst(rst),
        .in_valid(in_valid),
        .in_data(in_data),
        .out_valid(gold_out_valid),
        .out_data(gold_out_data)
    );

    gate gate_inst (
        .clk(clk),
        .rst(rst),
        .in_valid(in_valid),
        .in_data(in_data),
        .out_valid(gate_out_valid),
        .out_data(gate_out_data)
    );

    // First cycle: force a real reset via $initstate before comparing,
    // so the proof isn't defeated by unconstrained initial register state.
    always @(posedge clk) begin
        if ($initstate) begin
            assume (rst);
        end else begin
            assert (gold_out_valid == gate_out_valid && gold_out_data == gate_out_data);
        end
    end

endmodule

runs/web_f6e793600ee7_optimize_20260915T134737Z/round_3/attempt_1/candidate_1/formal/equiv_prove/engine_0/trace_induct.vcd
$version Generated by Yosys-SMTBMC $end
$timescale 1ns $end
$var integer 32 t smt_step $end
$var event 1 ! smt_clock $end
$scope module __eqcheck_top $end
$var wire 1 n0 clk $end
$scope module gate_inst $end
$var wire 19 n1 _00_ $end
$var wire 1 n2 _01_ $end
$var wire 8 n3 _02_ $end
$var wire 8 n4 _03_ $end
$var wire 8 n5 _04_ $end
$var wire 8 n6 _05_ $end
$var wire 8 n7 _06_ $end
$var wire 8 n8 _07_ $end
$var wire 1 n9 _08_ $end
$var wire 8 n10 _09_ $end
$var wire 8 n11 _10_ $end
$var wire 8 n12 _11_ $end
$var wire 8 n13 _12_ $end
$var wire 8 n14 _13_ $end
$var wire 8 n15 _14_ $end
$var wire 1 n16 clk $end
$var wire 8 n17 in_data $end
$var wire 1 n18 in_valid $end
$var wire 19 n19 out_data $end
$var wire 1 n20 out_valid $end
$var wire 19 n21 p0 $end
$var wire 19 n22 p1 $end
$var wire 19 n23 p2 $end
$var wire 19 n24 p3 $end
$var wire 19 n25 p4 $end
$var wire 19 n26 p5 $end
$var wire 1 n27 rst $end
$var wire 19 n28 s1 $end
$var wire 19 n29 s2 $end
$var wire 19 n30 s3 $end
$var wire 19 n31 s4 $end
$var wire 19 n32 s5 $end
$var wire 8 n33 t0 $end
$var wire 8 n34 t1 $end
$var wire 8 n35 t2 $end
$var wire 8 n36 t3 $end
$var wire 8 n37 t4 $end
$var wire 8 n38 t5 $end
$var wire 1 n39 vld $end
$upscope $end
$var wire 19 n40 gate_out_data $end
$var wire 1 n41 gate_out_valid $end
$scope module gold_inst $end
$var wire 19 n42 _00_ $end
$var wire 1 n43 _01_ $end
$var wire 8 n44 _02_ $end
$var wire 8 n45 _03_ $end
$var wire 8 n46 _04_ $end
$var wire 8 n47 _05_ $end
$var wire 8 n48 _06_ $end
$var wire 8 n49 _07_ $end
$var wire 1 n50 _08_ $end
$var wire 8 n51 _09_ $end
$var wire 8 n52 _10_ $end
$var wire 8 n53 _11_ $end
$var wire 8 n54 _12_ $end
$var wire 8 n55 _13_ $end
$var wire 8 n56 _14_ $end
$var wire 1 n57 clk $end
$var wire 8 n58 in_data $end
$var wire 1 n59 in_valid $end
$var wire 19 n60 out_data $end
$var wire 1 n61 out_valid $end
$var wire 19 n62 p0 $end
$var wire 19 n63 p1 $end
$var wire 19 n64 p2 $end
$var wire 19 n65 p3 $end
$var wire 19 n66 p4 $end
$var wire 19 n67 p5 $end
$var wire 1 n68 rst $end
$var wire 19 n69 s1 $end
$var wire 19 n70 s2 $end
$var wire 19 n71 s3 $end
$var wire 19 n72 s4 $end
$var wire 19 n73 s5 $end
$var wire 8 n74 t0 $end
$var wire 8 n75 t1 $end
$var wire 8 n76 t2 $end
$var wire 8 n77 t3 $end
$var wire 8 n78 t4 $end
$var wire 8 n79 t5 $end
$var wire 1 n80 vld $end
$upscope $end
$var wire 19 n81 gold_out_data $end
$var wire 1 n82 gold_out_valid $end
$var wire 8 n83 in_data $end
$var wire 1 n84 in_valid $end
$var wire 1 n85 rst $end
$upscope $end
$enddefinitions $end
#0
1!
b00000000000000000000000000000000 t
b1 n0
b1 n16
b1 n57
b0000000000010101101 n1
b0 n2
b01101111 n3
b01011000 n4
b00111111 n5
b00101100 n6
b01100111 n7
b10100110 n8
b0 n9
b10100110 n10
b01100111 n11
b00101100 n12
b00111111 n13
b01011000 n14
b01101111 n15
b00000000 n17
b0 n18
b0000000000000000000 n19
b0 n20
b0000000100111111001 n21
b1111110111111011000 n22
b0000001001111101111 n23
b0000000110111101100 n24
b1111110110100010111 n25
b1111111011111101010 n26
b0 n27
b1111111100111010001 n28
b0000010000111011011 n29
b1111110010100000001 n30
b0000001101110101100 n31
b0000000000010101101 n32
b01101111 n33
b01011000 n34
b00111111 n35
b00101100 n36
b01100111 n37
b10100110 n38
b0 n39
b0000000000000000000 n40
b0 n41
b0000000000010101101 n42
b0 n43
b11011010 n44
b10101110 n45
b01110111 n46
b10100001 n47
b01101001 n48
b00001000 n49
b0 n50
b00001000 n51
b01101001 n52
b10100001 n53
b01110111 n54
b10101110 n55
b11011010 n56
b00000000 n58
b0 n59
b0000000000000000000 n60
b0 n61
b1111111110010010110 n62
b0000000111100001110 n63
b0000010010110100111 n64
b1111110000111110001 n65
b1111110110010111001 n66
b0000000000010111000 n67
b0 n68
b0000000101110100100 n69
b0000011000101001011 n70
b0000001001100111100 n71
b1111111111111110101 n72
b0000000000010101101 n73
b11011010 n74
b10101110 n75
b01110111 n76
b10100001 n77
b01101001 n78
b00001000 n79
b0 n80
b0000000000000000000 n81
b0 n82
b00000000 n83
b0 n84
b0 n85
#5
b0 n0
b0 n16
b0 n57
#10
1!
b00000000000000000000000000000001 t
b1 n0
b1 n16
b1 n57
b0000000000010101101 n1
b0 n2
b01101111 n3
b01011000 n4
b00111111 n5
b00101100 n6
b01100111 n7
b10100110 n8
b0 n9
b10100110 n10
b01100111 n11
b00101100 n12
b00111111 n13
b01011000 n14
b01101111 n15
b00000000 n17
b0 n18
b0000000000010101101 n19
b0 n20
b0000000100111111001 n21
b1111110111111011000 n22
b0000001001111101111 n23
b0000000110111101100 n24
b1111110110100010111 n25
b1111111011111101010 n26
b0 n27
b1111111100111010001 n28
b0000010000111011011 n29
b1111110010100000001 n30
b0000001101110101100 n31
b0000000000010101101 n32
b01101111 n33
b01011000 n34
b00111111 n35
b00101100 n36
b01100111 n37
b10100110 n38
b0 n39
b0000000000010101101 n40
b0 n41
b0000000000010101101 n42
b0 n43
b11011010 n44
b10101110 n45
b01110111 n46
b10100001 n47
b01101001 n48
b00001000 n49
b0 n50
b00001000 n51
b01101001 n52
b10100001 n53
b01110111 n54
b10101110 n55
b11011010 n56
b00000000 n58
b0 n59
b0000000000010101101 n60
b0 n61
b1111111110010010110 n62
b0000000111100001110 n63
b0000010010110100111 n64
b1111110000111110001 n65
b1111110110010111001 n66
b0000000000010111000 n67
b0 n68
b0000000101110100100 n69
b0000011000101001011 n70
b0000001001100111100 n71
b1111111111111110101 n72
b0000000000010101101 n73
b11011010 n74
b10101110 n75
b01110111 n76
b10100001 n77
b01101001 n78
b00001000 n79
b0 n80
b0000000000010101101 n81
b0 n82
b00000000 n83
b0 n84
b0 n85
#15
b0 n0
b0 n16
b0 n57
#20
1!
b00000000000000000000000000000010 t
b1 n0
b1 n16
b1 n57
b0000000000010101101 n1
b0 n2
b01101111 n3
b01011000 n4
b00111111 n5
b00101100 n6
b01100111 n7
b10100110 n8
b0 n9
b10100110 n10
b01100111 n11
b00101100 n12
b00111111 n13
b01011000 n14
b01101111 n15
b00000000 n17
b0 n18
b0000000000010101101 n19
b0 n20
b0000000100111111001 n21
b1111110111111011000 n22
b0000001001111101111 n23
b0000000110111101100 n24
b1111110110100010111 n25
b1111111011111101010 n26
b0 n27
b1111111100111010001 n28
b0000010000111011011 n29
b1111110010100000001 n30
b0000001101110101100 n31
b0000000000010101101 n32
b01101111 n33
b01011000 n34
b00111111 n35
b00101100 n36
b01100111 n37
b10100110 n38
b0 n39
b0000000000010101101 n40
b0 n41
b0000000000010101101 n42
b0 n43
b11011010 n44
b10101110 n45
b01110111 n46
b10100001 n47
b01101001 n48
b00001000 n49
b0 n50
b00001000 n51
b01101001 n52
b10100001 n53
b01110111 n54
b10101110 n55
b11011010 n56
b00000000 n58
b0 n59
b0000000000010101101 n60
b0 n61
b1111111110010010110 n62
b0000000111100001110 n63
b0000010010110100111 n64
b1111110000111110001 n65
b1111110110010111001 n66
b0000000000010111000 n67
b0 n68
b0000000101110100100 n69
b0000011000101001011 n70
b0000001001100111100 n71
b1111111111111110101 n72
b0000000000010101101 n73
b11011010 n74
b10101110 n75
b01110111 n76
b10100001 n77
b01101001 n78
b00001000 n79
b0 n80
b0000000000010101101 n81
b0 n82
b00000000 n83
b0 n84
b0 n85
#25
b0 n0
b0 n16
b0 n57
#30
1!
b00000000000000000000000000000011 t
b1 n0
b1 n16
b1 n57
b0000000000010101101 n1
b0 n2
b01101111 n3
b01011000 n4
b00111111 n5
b00101100 n6
b01100111 n7
b10100110 n8
b0 n9
b10100110 n10
b01100111 n11
b00101100 n12
b00111111 n13
b01011000 n14
b01101111 n15
b00000000 n17
b0 n18
b0000000000010101101 n19
b0 n20
b0000000100111111001 n21
b1111110111111011000 n22
b0000001001111101111 n23
b0000000110111101100 n24
b1111110110100010111 n25
b1111111011111101010 n26
b0 n27
b1111111100111010001 n28
b0000010000111011011 n29
b1111110010100000001 n30
b0000001101110101100 n31
b0000000000010101101 n32
b01101111 n33
b01011000 n34
b00111111 n35
b00101100 n36
b01100111 n37
b10100110 n38
b0 n39
b0000000000010101101 n40
b0 n41
b0000000000010101101 n42
b0 n43
b11011010 n44
b10101110 n45
b01110111 n46
b10100001 n47
b01101001 n48
b00001000 n49
b0 n50
b00001000 n51
b01101001 n52
b10100001 n53
b01110111 n54
b10101110 n55
b11011010 n56
b00000000 n58
b0 n59
b0000000000010101101 n60
b0 n61
b1111111110010010110 n62
b0000000111100001110 n63
b0000010010110100111 n64
b1111110000111110001 n65
b1111110110010111001 n66
b0000000000010111000 n67
b0 n68
b0000000101110100100 n69
b0000011000101001011 n70
b0000001001100111100 n71
b1111111111111110101 n72
b0000000000010101101 n73
b11011010 n74
b10101110 n75
b01110111 n76
b10100001 n77
b01101001 n78
b00001000 n79
b0 n80
b0000000000010101101 n81
b0 n82
b00000000 n83
b0 n84
b0 n85
#35
b0 n0
b0 n16
b0 n57
#40
1!
b00000000000000000000000000000100 t
b1 n0
b1 n16
b1 n57
b0000000000010101101 n1
b0 n2
b01101111 n3
b01011000 n4
b00111111 n5
b00101100 n6
b01100111 n7
b10100110 n8
b0 n9
b10100110 n10
b01100111 n11
b00101100 n12
b00111111 n13
b01011000 n14
b01101111 n15
b00000000 n17
b0 n18
b0000000000010101101 n19
b0 n20
b0000000100111111001 n21
b1111110111111011000 n22
b0000001001111101111 n23
b0000000110111101100 n24
b1111110110100010111 n25
b1111111011111101010 n26
b0 n27
b1111111100111010001 n28
b0000010000111011011 n29
b1111110010100000001 n30
b0000001101110101100 n31
b0000000000010101101 n32
b01101111 n33
b01011000 n34
b00111111 n35
b00101100 n36
b01100111 n37
b10100110 n38
b0 n39
b0000000000010101101 n40
b0 n41
b0000000000010101101 n42
b0 n43
b11011010 n44
b10101110 n45
b01110111 n46
b10100001 n47
b01101001 n48
b00001000 n49
b0 n50
b00001000 n51
b01101001 n52
b10100001 n53
b01110111 n54
b10101110 n55
b11011010 n56
b00000000 n58
b0 n59
b0000000000010101101 n60
b0 n61
b1111111110010010110 n62
b0000000111100001110 n63
b0000010010110100111 n64
b1111110000111110001 n65
b1111110110010111001 n66
b0000000000010111000 n67
b0 n68
b0000000101110100100 n69
b0000011000101001011 n70
b0000001001100111100 n71
b1111111111111110101 n72
b0000000000010101101 n73
b11011010 n74
b10101110 n75
b01110111 n76
b10100001 n77
b01101001 n78
b00001000 n79
b0 n80
b0000000000010101101 n81
b0 n82
b00000000 n83
b0 n84
b0 n85
#45
b0 n0
b0 n16
b0 n57
#50
1!
b00000000000000000000000000000101 t
b1 n0
b1 n16
b1 n57
b0000000000010101101 n1
b0 n2
b01101111 n3
b01011000 n4
b00111111 n5
b00101100 n6
b01100111 n7
b10100110 n8
b0 n9
b10100110 n10
b01100111 n11
b00101100 n12
b00111111 n13
b01011000 n14
b01101111 n15
b00000000 n17
b0 n18
b0000000000010101101 n19
b0 n20
b0000000100111111001 n21
b1111110111111011000 n22
b0000001001111101111 n23
b0000000110111101100 n24
b1111110110100010111 n25
b1111111011111101010 n26
b0 n27
b1111111100111010001 n28
b0000010000111011011 n29
b1111110010100000001 n30
b0000001101110101100 n31
b0000000000010101101 n32
b01101111 n33
b01011000 n34
b00111111 n35
b00101100 n36
b01100111 n37
b10100110 n38
b0 n39
b0000000000010101101 n40
b0 n41
b0000000000010101101 n42
b0 n43
b11011010 n44
b10101110 n45
b01110111 n46
b10100001 n47
b01101001 n48
b00001000 n49
b0 n50
b00001000 n51
b01101001 n52
b10100001 n53
b01110111 n54
b10101110 n55
b11011010 n56
b00000000 n58
b0 n59
b0000000000010101101 n60
b0 n61
b1111111110010010110 n62
b0000000111100001110 n63
b0000010010110100111 n64
b1111110000111110001 n65
b1111110110010111001 n66
b0000000000010111000 n67
b0 n68
b0000000101110100100 n69
b0000011000101001011 n70
b0000001001100111100 n71
b1111111111111110101 n72
b0000000000010101101 n73
b11011010 n74
b10101110 n75
b01110111 n76
b10100001 n77
b01101001 n78
b00001000 n79
b0 n80
b0000000000010101101 n81
b0 n82
b00000000 n83
b0 n84
b0 n85
#55
b0 n0
b0 n16
b0 n57
#60
1!
b00000000000000000000000000000110 t
b1 n0
b1 n16
b1 n57
b0000000000010101101 n1
b0 n2
b01101111 n3
b01011000 n4
b00111111 n5
b00101100 n6
b01100111 n7
b10100110 n8
b0 n9
b10100110 n10
b01100111 n11
b00101100 n12
b00111111 n13
b01011000 n14
b01101111 n15
b00000000 n17
b0 n18
b0000000000010101101 n19
b0 n20
b0000000100111111001 n21
b1111110111111011000 n22
b0000001001111101111 n23
b0000000110111101100 n24
b1111110110100010111 n25
b1111111011111101010 n26
b0 n27
b1111111100111010001 n28
b0000010000111011011 n29
b1111110010100000001 n30
b0000001101110101100 n31
b0000000000010101101 n32
b01101111 n33
b01011000 n34
b00111111 n35
b00101100 n36
b01100111 n37
b10100110 n38
b0 n39
b0000000000010101101 n40
b0 n41
b0000000000010101101 n42
b0 n43
b11011010 n44
b10101110 n45
b01110111 n46
b10100001 n47
b01101001 n48
b00001000 n49
b0 n50
b00001000 n51
b01101001 n52
b10100001 n53
b01110111 n54
b10101110 n55
b11011010 n56
b00000000 n58
b0 n59
b0000000000010101101 n60
b0 n61
b1111111110010010110 n62
b0000000111100001110 n63
b0000010010110100111 n64
b1111110000111110001 n65
b1111110110010111001 n66
b0000000000010111000 n67
b0 n68
b0000000101110100100 n69
b0000011000101001011 n70
b0000001001100111100 n71
b1111111111111110101 n72
b0000000000010101101 n73
b11011010 n74
b10101110 n75
b01110111 n76
b10100001 n77
b01101001 n78
b00001000 n79
b0 n80
b0000000000010101101 n81
b0 n82
b00000000 n83
b0 n84
b0 n85
#65
b0 n0
b0 n16
b0 n57
#70
1!
b00000000000000000000000000000111 t
b1 n0
b1 n16
b1 n57
b0000000000010101101 n1
b0 n2
b01101111 n3
b01011000 n4
b00111111 n5
b00101100 n6
b01100111 n7
b10100110 n8
b0 n9
b10100110 n10
b01100111 n11
b00101100 n12
b00111111 n13
b01011000 n14
b01101111 n15
b00000000 n17
b0 n18
b0000000000010101101 n19
b0 n20
b0000000100111111001 n21
b1111110111111011000 n22
b0000001001111101111 n23
b0000000110111101100 n24
b1111110110100010111 n25
b1111111011111101010 n26
b0 n27
b1111111100111010001 n28
b0000010000111011011 n29
b1111110010100000001 n30
b0000001101110101100 n31
b0000000000010101101 n32
b01101111 n33
b01011000 n34
b00111111 n35
b00101100 n36
b01100111 n37
b10100110 n38
b0 n39
b0000000000010101101 n40
b0 n41
b0000000000010101101 n42
b0 n43
b11011010 n44
b10101110 n45
b01110111 n46
b10100001 n47
b01101001 n48
b00001000 n49
b0 n50
b00001000 n51
b01101001 n52
b10100001 n53
b01110111 n54
b10101110 n55
b11011010 n56
b00000000 n58
b0 n59
b0000000000010101101 n60
b0 n61
b1111111110010010110 n62
b0000000111100001110 n63
b0000010010110100111 n64
b1111110000111110001 n65
b1111110110010111001 n66
b0000000000010111000 n67
b0 n68
b0000000101110100100 n69
b0000011000101001011 n70
b0000001001100111100 n71
b1111111111111110101 n72
b0000000000010101101 n73
b11011010 n74
b10101110 n75
b01110111 n76
b10100001 n77
b01101001 n78
b00001000 n79
b0 n80
b0000000000010101101 n81
b0 n82
b00000000 n83
b0 n84
b0 n85
#75
b0 n0
b0 n16
b0 n57
#80
1!
b00000000000000000000000000001000 t
b1 n0
b1 n16
b1 n57
b0000000000010101101 n1
b0 n2
b01101111 n3
b01011000 n4
b00111111 n5
b00101100 n6
b01100111 n7
b10100110 n8
b0 n9
b10100110 n10
b01100111 n11
b00101100 n12
b00111111 n13
b01011000 n14
b01101111 n15
b00000000 n17
b0 n18
b0000000000010101101 n19
b0 n20
b0000000100111111001 n21
b1111110111111011000 n22
b0000001001111101111 n23
b0000000110111101100 n24
b1111110110100010111 n25
b1111111011111101010 n26
b0 n27
b1111111100111010001 n28
b0000010000111011011 n29
b1111110010100000001 n30
b0000001101110101100 n31
b0000000000010101101 n32
b01101111 n33
b01011000 n34
b00111111 n35
b00101100 n36
b01100111 n37
b10100110 n38
b0 n39
b0000000000010101101 n40
b0 n41
b0000000000010101101 n42
b0 n43
b11011010 n44
b10101110 n45
b01110111 n46
b10100001 n47
b01101001 n48
b00001000 n49
b0 n50
b00001000 n51
b01101001 n52
b10100001 n53
b01110111 n54
b10101110 n55
b11011010 n56
b00000000 n58
b0 n59
b0000000000010101101 n60
b0 n61
b1111111110010010110 n62
b0000000111100001110 n63
b0000010010110100111 n64
b1111110000111110001 n65
b1111110110010111001 n66
b0000000000010111000 n67
b0 n68
b0000000101110100100 n69
b0000011000101001011 n70
b0000001001100111100 n71
b1111111111111110101 n72
b0000000000010101101 n73
b11011010 n74
b10101110 n75
b01110111 n76
b10100001 n77
b01101001 n78
b00001000 n79
b0 n80
b0000000000010101101 n81
b0 n82
b00000000 n83
b0 n84
b0 n85
#85
b0 n0
b0 n16
b0 n57
#90
1!
b00000000000000000000000000001001 t
b1 n0
b1 n16
b1 n57
b0000000000010101101 n1
b0 n2
b01101111 n3
b01011000 n4
b00111111 n5
b00101100 n6
b01100111 n7
b10100110 n8
b0 n9
b10100110 n10
b01100111 n11
b00101100 n12
b00111111 n13
b01011000 n14
b01101111 n15
b00000000 n17
b0 n18
b0000000000010101101 n19
b0 n20
b0000000100111111001 n21
b1111110111111011000 n22
b0000001001111101111 n23
b0000000110111101100 n24
b1111110110100010111 n25
b1111111011111101010 n26
b0 n27
b1111111100111010001 n28
b0000010000111011011 n29
b1111110010100000001 n30
b0000001101110101100 n31
b0000000000010101101 n32
b01101111 n33
b01011000 n34
b00111111 n35
b00101100 n36
b01100111 n37
b10100110 n38
b0 n39
b0000000000010101101 n40
b0 n41
b0000000000010101101 n42
b0 n43
b11011010 n44
b10101110 n45
b01110111 n46
b10100001 n47
b01101001 n48
b00001000 n49
b0 n50
b00001000 n51
b01101001 n52
b10100001 n53
b01110111 n54
b10101110 n55
b11011010 n56
b00000000 n58
b0 n59
b0000000000010101101 n60
b0 n61
b1111111110010010110 n62
b0000000111100001110 n63
b0000010010110100111 n64
b1111110000111110001 n65
b1111110110010111001 n66
b0000000000010111000 n67
b0 n68
b0000000101110100100 n69
b0000011000101001011 n70
b0000001001100111100 n71
b1111111111111110101 n72
b0000000000010101101 n73
b11011010 n74
b10101110 n75
b01110111 n76
b10100001 n77
b01101001 n78
b00001000 n79
b0 n80
b0000000000010101101 n81
b0 n82
b00000000 n83
b0 n84
b0 n85
#95
b0 n0
b0 n16
b0 n57
#100
1!
b00000000000000000000000000001010 t
b1 n0
b1 n16
b1 n57
b0000000000010101101 n1
b0 n2
b01101111 n3
b01011000 n4
b00111111 n5
b00101100 n6
b01100111 n7
b10100110 n8
b0 n9
b10100110 n10
b01100111 n11
b00101100 n12
b00111111 n13
b01011000 n14
b01101111 n15
b00000000 n17
b0 n18
b0000000000010101101 n19
b0 n20
b0000000100111111001 n21
b1111110111111011000 n22
b0000001001111101111 n23
b0000000110111101100 n24
b1111110110100010111 n25
b1111111011111101010 n26
b0 n27
b1111111100111010001 n28
b0000010000111011011 n29
b1111110010100000001 n30
b0000001101110101100 n31
b0000000000010101101 n32
b01101111 n33
b01011000 n34
b00111111 n35
b00101100 n36
b01100111 n37
b10100110 n38
b0 n39
b0000000000010101101 n40
b0 n41
b0000000000010101101 n42
b0 n43
b11011010 n44
b10101110 n45
b01110111 n46
b10100001 n47
b01101001 n48
b00001000 n49
b0 n50
b00001000 n51
b01101001 n52
b10100001 n53
b01110111 n54
b10101110 n55
b11011010 n56
b00000000 n58
b0 n59
b0000000000010101101 n60
b0 n61
b1111111110010010110 n62
b0000000111100001110 n63
b0000010010110100111 n64
b1111110000111110001 n65
b1111110110010111001 n66
b0000000000010111000 n67
b0 n68
b0000000101110100100 n69
b0000011000101001011 n70
b0000001001100111100 n71
b1111111111111110101 n72
b0000000000010101101 n73
b11011010 n74
b10101110 n75
b01110111 n76
b10100001 n77
b01101001 n78
b00001000 n79
b0 n80
b0000000000010101101 n81
b0 n82
b00000000 n83
b0 n84
b0 n85
#105
b0 n0
b0 n16
b0 n57
#110
1!
b00000000000000000000000000001011 t
b1 n0
b1 n16
b1 n57
b0000000000010101101 n1
b0 n2
b01101111 n3
b01011000 n4
b00111111 n5
b00101100 n6
b01100111 n7
b10100110 n8
b0 n9
b10100110 n10
b01100111 n11
b00101100 n12
b00111111 n13
b01011000 n14
b01101111 n15
b00000000 n17
b0 n18
b0000000000010101101 n19
b0 n20
b0000000100111111001 n21
b1111110111111011000 n22
b0000001001111101111 n23
b0000000110111101100 n24
b1111110110100010111 n25
b1111111011111101010 n26
b0 n27
b1111111100111010001 n28
b0000010000111011011 n29
b1111110010100000001 n30
b0000001101110101100 n31
b0000000000010101101 n32
b01101111 n33
b01011000 n34
b00111111 n35
b00101100 n36
b01100111 n37
b10100110 n38
b0 n39
b0000000000010101101 n40
b0 n41
b0000000000010101101 n42
b0 n43
b11011010 n44
b10101110 n45
b01110111 n46
b10100001 n47
b01101001 n48
b00001000 n49
b0 n50
b00001000 n51
b01101001 n52
b10100001 n53
b01110111 n54
b10101110 n55
b11011010 n56
b00000000 n58
b0 n59
b0000000000010101101 n60
b0 n61
b1111111110010010110 n62
b0000000111100001110 n63
b0000010010110100111 n64
b1111110000111110001 n65
b1111110110010111001 n66
b0000000000010111000 n67
b0 n68
b0000000101110100100 n69
b0000011000101001011 n70
b0000001001100111100 n71
b1111111111111110101 n72
b0000000000010101101 n73
b11011010 n74
b10101110 n75
b01110111 n76
b10100001 n77
b01101001 n78
b00001000 n79
b0 n80
b0000000000010101101 n81
b0 n82
b00000000 n83
b0 n84
b0 n85
#115
b0 n0
b0 n16
b0 n57
