runs/web_b5258d7e4ad0_optimize_20260914T144523Z/round_3/attempt_1/candidate_1/formal/equiv_prove/src/gold_gate.v
/* Generated by Yosys 0.68+195 (git sha1 435977e97-dirty, Release, Clang /usr/bin/clang++ 21.1.8) */

module gate(clk, rst, in_valid, in_data, out_valid, out_data);
  input clk;
  wire clk;
  input rst;
  wire rst;
  input in_valid;
  wire in_valid;
  input signed [7:0] in_data;
  wire signed [7:0] in_data;
  output out_valid;
  reg out_valid;
  output signed [18:0] out_data;
  reg signed [18:0] out_data;
  wire [18:0] _00_;
  wire _01_;
  wire [18:0] _02_;
  wire [18:0] _03_;
  wire [7:0] _04_;
  wire [7:0] _05_;
  wire [7:0] _06_;
  wire [7:0] _07_;
  wire [7:0] _08_;
  wire [7:0] _09_;
  wire _10_;
  wire _11_;
  wire signed [18:0] _12_;
  wire [7:0] _13_;
  wire [7:0] _14_;
  wire [7:0] _15_;
  wire [7:0] _16_;
  wire [7:0] _17_;
  wire [7:0] _18_;
  wire signed [18:0] p0;
  wire signed [18:0] p1;
  wire signed [18:0] p2;
  wire signed [18:0] p3;
  wire signed [18:0] p4;
  wire signed [18:0] p5;
  wire signed [18:0] sa;
  wire signed [18:0] sa_l1;
  reg signed [18:0] sa_r;
  wire signed [18:0] sb;
  wire signed [18:0] sb_l1;
  reg signed [18:0] sb_r;
  reg signed [7:0] t0;
  reg signed [7:0] t1;
  reg signed [7:0] t2;
  reg signed [7:0] t3;
  reg signed [7:0] t4;
  reg signed [7:0] t5;
  reg vld;
  reg vld2;
  assign sa_l1 = $signed(p0) + $signed(p1);
  assign sa = $signed(sa_l1) + $signed(p2);
  assign sb_l1 = $signed(p3) + $signed(p4);
  assign sb = $signed(sb_l1) + $signed(p5);
  assign _12_ = $signed(sa_r) + $signed(sb_r);
  assign p0 = $signed(t0) * $signed(8'h17);
  assign p1 = $signed(t1) * $signed(8'hd1);
  assign p2 = $signed(t2) * $signed(8'h51);
  assign p3 = $signed(t3) * $signed(8'h51);
  assign p4 = $signed(t4) * $signed(8'hd1);
  assign p5 = $signed(t5) * $signed(8'h17);
  always @(posedge clk)
    out_valid <= _01_;
  always @(posedge clk)
    out_data <= _00_;
  always @(posedge clk)
    sb_r <= _03_;
  always @(posedge clk)
    sa_r <= _02_;
  always @(posedge clk)
    vld2 <= _10_;
  always @(posedge clk)
    vld <= _11_;
  always @(posedge clk)
    t0 <= _04_;
  always @(posedge clk)
    t1 <= _05_;
  always @(posedge clk)
    t2 <= _06_;
  always @(posedge clk)
    t3 <= _07_;
  always @(posedge clk)
    t4 <= _08_;
  always @(posedge clk)
    t5 <= _09_;
  assign _01_ = rst ? 1'h0 : vld2;
  assign _00_ = rst ? 19'h00000 : _12_;
  assign _10_ = rst ? 1'h0 : vld;
  assign _03_ = rst ? 19'h00000 : sb;
  assign _02_ = rst ? 19'h00000 : sa;
  assign _11_ = rst ? 1'h0 : in_valid;
  assign _13_ = in_valid ? t4 : t5;
  assign _09_ = rst ? 8'h00 : _13_;
  assign _14_ = in_valid ? t3 : t4;
  assign _08_ = rst ? 8'h00 : _14_;
  assign _15_ = in_valid ? t2 : t3;
  assign _07_ = rst ? 8'h00 : _15_;
  assign _16_ = in_valid ? t1 : t2;
  assign _06_ = rst ? 8'h00 : _16_;
  assign _17_ = in_valid ? t0 : t1;
  assign _05_ = rst ? 8'h00 : _17_;
  assign _18_ = in_valid ? in_data : t0;
  assign _04_ = rst ? 8'h00 : _18_;
endmodule

module gold(clk, rst, in_valid, in_data, out_valid, out_data);
  input clk;
  wire clk;
  input rst;
  wire rst;
  input in_valid;
  wire in_valid;
  input signed [7:0] in_data;
  wire signed [7:0] in_data;
  output out_valid;
  reg out_valid;
  output signed [18:0] out_data;
  reg signed [18:0] out_data;
  wire [18:0] _00_;
  wire _01_;
  wire [7:0] _02_;
  wire [7:0] _03_;
  wire [7:0] _04_;
  wire [7:0] _05_;
  wire [7:0] _06_;
  wire [7:0] _07_;
  wire _08_;
  wire [7:0] _09_;
  wire [7:0] _10_;
  wire [7:0] _11_;
  wire [7:0] _12_;
  wire [7:0] _13_;
  wire [7:0] _14_;
  wire signed [18:0] p0;
  wire signed [18:0] p1;
  wire signed [18:0] p2;
  wire signed [18:0] p3;
  wire signed [18:0] p4;
  wire signed [18:0] p5;
  wire signed [18:0] s1;
  wire signed [18:0] s2;
  wire signed [18:0] s3;
  wire signed [18:0] s4;
  wire signed [18:0] s5;
  reg signed [7:0] t0;
  reg signed [7:0] t1;
  reg signed [7:0] t2;
  reg signed [7:0] t3;
  reg signed [7:0] t4;
  reg signed [7:0] t5;
  reg vld;
  assign s1 = $signed(p0) + $signed(p1);
  assign s2 = $signed(s1) + $signed(p2);
  assign s3 = $signed(s2) + $signed(p3);
  assign s4 = $signed(s3) + $signed(p4);
  assign s5 = $signed(s4) + $signed(p5);
  assign p0 = $signed(t0) * $signed(8'h17);
  assign p1 = $signed(t1) * $signed(8'hd1);
  assign p2 = $signed(t2) * $signed(8'h51);
  assign p3 = $signed(t3) * $signed(8'h51);
  assign p4 = $signed(t4) * $signed(8'hd1);
  assign p5 = $signed(t5) * $signed(8'h17);
  always @(posedge clk)
    out_valid <= _01_;
  always @(posedge clk)
    out_data <= _00_;
  always @(posedge clk)
    vld <= _08_;
  always @(posedge clk)
    t0 <= _02_;
  always @(posedge clk)
    t1 <= _03_;
  always @(posedge clk)
    t2 <= _04_;
  always @(posedge clk)
    t3 <= _05_;
  always @(posedge clk)
    t4 <= _06_;
  always @(posedge clk)
    t5 <= _07_;
  assign _01_ = rst ? 1'h0 : vld;
  assign _00_ = rst ? 19'h00000 : s5;
  assign _08_ = rst ? 1'h0 : in_valid;
  assign _09_ = in_valid ? t4 : t5;
  assign _07_ = rst ? 8'h00 : _09_;
  assign _10_ = in_valid ? t3 : t4;
  assign _06_ = rst ? 8'h00 : _10_;
  assign _11_ = in_valid ? t2 : t3;
  assign _05_ = rst ? 8'h00 : _11_;
  assign _12_ = in_valid ? t1 : t2;
  assign _04_ = rst ? 8'h00 : _12_;
  assign _13_ = in_valid ? t0 : t1;
  assign _03_ = rst ? 8'h00 : _13_;
  assign _14_ = in_valid ? in_data : t0;
  assign _02_ = rst ? 8'h00 : _14_;
endmodule

runs/web_b5258d7e4ad0_optimize_20260914T144523Z/round_3/attempt_1/candidate_1/formal/equiv_prove/src/eqcheck_wrapper.v
module __eqcheck_top (
    input wire clk,
    input wire rst,
    input wire in_valid,
    input wire [7:0] in_data
);

    wire gold_out_valid;
    wire gate_out_valid;
    wire [18:0] gold_out_data;
    wire [18:0] gate_out_data;

    gold gold_inst (
        .clk(clk),
        .rst(rst),
        .in_valid(in_valid),
        .in_data(in_data),
        .out_valid(gold_out_valid),
        .out_data(gold_out_data)
    );

    gate gate_inst (
        .clk(clk),
        .rst(rst),
        .in_valid(in_valid),
        .in_data(in_data),
        .out_valid(gate_out_valid),
        .out_data(gate_out_data)
    );

    // Latency offset of 1 cycle(s): the candidate produces its
    // outputs later than the baseline (added pipeline stages), so the baseline's
    // outputs are delayed by that many cycles before being compared.
    reg gold_out_valid_d1;
    reg [18:0] gold_out_data_d1;

    always @(posedge clk) begin
        gold_out_valid_d1 <= gold_out_valid;
        gold_out_data_d1 <= gold_out_data;
    end

    // Comparison is suppressed until the delay pipeline has filled.
    reg [7:0] warmup = 8'd0;
    always @(posedge clk) begin
        if (rst) warmup <= 8'd0;
        else if (warmup < 8'd1) warmup <= warmup + 8'd1;
    end

    // First cycle: force a real reset via $initstate before comparing,
    // so the proof isn't defeated by unconstrained initial register state.
    always @(posedge clk) begin
        if ($initstate) begin
            assume (rst);
        end else begin
            if (warmup >= 8'd1) assert (gold_out_valid_d1 == gate_out_valid && gold_out_data_d1 == gate_out_data);
        end
    end

endmodule

runs/web_b5258d7e4ad0_optimize_20260914T144523Z/round_3/attempt_1/candidate_1/formal/equiv_prove/engine_0/trace_induct.vcd
$version Generated by Yosys-SMTBMC $end
$timescale 1ns $end
$var integer 32 t smt_step $end
$var event 1 ! smt_clock $end
$scope module __eqcheck_top $end
$var wire 1 n0 clk $end
$scope module gate_inst $end
$var wire 19 n1 _00_ $end
$var wire 1 n2 _01_ $end
$var wire 19 n3 _02_ $end
$var wire 19 n4 _03_ $end
$var wire 8 n5 _04_ $end
$var wire 8 n6 _05_ $end
$var wire 8 n7 _06_ $end
$var wire 8 n8 _07_ $end
$var wire 8 n9 _08_ $end
$var wire 8 n10 _09_ $end
$var wire 1 n11 _10_ $end
$var wire 1 n12 _11_ $end
$var wire 19 n13 _12_ $end
$var wire 8 n14 _13_ $end
$var wire 8 n15 _14_ $end
$var wire 8 n16 _15_ $end
$var wire 8 n17 _16_ $end
$var wire 8 n18 _17_ $end
$var wire 8 n19 _18_ $end
$var wire 1 n20 clk $end
$var wire 8 n21 in_data $end
$var wire 1 n22 in_valid $end
$var wire 19 n23 out_data $end
$var wire 1 n24 out_valid $end
$var wire 19 n25 p0 $end
$var wire 19 n26 p1 $end
$var wire 19 n27 p2 $end
$var wire 19 n28 p3 $end
$var wire 19 n29 p4 $end
$var wire 19 n30 p5 $end
$var wire 1 n31 rst $end
$var wire 19 n32 sa $end
$var wire 19 n33 sa_l1 $end
$var wire 19 n34 sa_r $end
$var wire 19 n35 sb $end
$var wire 19 n36 sb_l1 $end
$var wire 19 n37 sb_r $end
$var wire 8 n38 t0 $end
$var wire 8 n39 t1 $end
$var wire 8 n40 t2 $end
$var wire 8 n41 t3 $end
$var wire 8 n42 t4 $end
$var wire 8 n43 t5 $end
$var wire 1 n44 vld $end
$var wire 1 n45 vld2 $end
$upscope $end
$var wire 19 n46 gate_out_data $end
$var wire 1 n47 gate_out_valid $end
$scope module gold_inst $end
$var wire 19 n48 _00_ $end
$var wire 1 n49 _01_ $end
$var wire 8 n50 _02_ $end
$var wire 8 n51 _03_ $end
$var wire 8 n52 _04_ $end
$var wire 8 n53 _05_ $end
$var wire 8 n54 _06_ $end
$var wire 8 n55 _07_ $end
$var wire 1 n56 _08_ $end
$var wire 8 n57 _09_ $end
$var wire 8 n58 _10_ $end
$var wire 8 n59 _11_ $end
$var wire 8 n60 _12_ $end
$var wire 8 n61 _13_ $end
$var wire 8 n62 _14_ $end
$var wire 1 n63 clk $end
$var wire 8 n64 in_data $end
$var wire 1 n65 in_valid $end
$var wire 19 n66 out_data $end
$var wire 1 n67 out_valid $end
$var wire 19 n68 p0 $end
$var wire 19 n69 p1 $end
$var wire 19 n70 p2 $end
$var wire 19 n71 p3 $end
$var wire 19 n72 p4 $end
$var wire 19 n73 p5 $end
$var wire 1 n74 rst $end
$var wire 19 n75 s1 $end
$var wire 19 n76 s2 $end
$var wire 19 n77 s3 $end
$var wire 19 n78 s4 $end
$var wire 19 n79 s5 $end
$var wire 8 n80 t0 $end
$var wire 8 n81 t1 $end
$var wire 8 n82 t2 $end
$var wire 8 n83 t3 $end
$var wire 8 n84 t4 $end
$var wire 8 n85 t5 $end
$var wire 1 n86 vld $end
$upscope $end
$var wire 19 n87 gold_out_data $end
$var wire 19 n88 gold_out_data_d1 $end
$var wire 1 n89 gold_out_valid $end
$var wire 1 n90 gold_out_valid_d1 $end
$var wire 8 n91 in_data $end
$var wire 1 n92 in_valid $end
$var wire 1 n93 rst $end
$var wire 8 n94 warmup $end
$upscope $end
$enddefinitions $end
#0
1!
b00000000000000000000000000000000 t
b1 n0
b1 n20
b1 n63
b0000000000000000000 n1
b0 n2
b0000001000000000111 n3
b1111110110101110111 n4
b00011010 n5
b11010001 n6
b00010000 n7
b11101101 n8
b00001001 n9
b10000111 n10
b0 n11
b0 n12
b0000000000000000000 n13
b10000111 n14
b00001001 n15
b11101101 n16
b00010000 n17
b11010001 n18
b00011010 n19
b00000000 n21
b0 n22
b0000000000000000000 n23
b0 n24
b0000000001001010110 n25
b0000000100010100001 n26
b0000000010100010000 n27
b1111111100111111101 n28
b1111111111001011001 n29
b1111111010100100001 n30
b0 n31
b0000001000000000111 n32
b0000000101011110111 n33
b0000000000000000000 n34
b1111110110101110111 n35
b1111111100001010110 n36
b0000000000000000000 n37
b00011010 n38
b11010001 n39
b00010000 n40
b11101101 n41
b00001001 n42
b10000111 n43
b0 n44
b0 n45
b0000000000000000000 n46
b0 n47
b1111111110101111110 n48
b0 n49
b10110001 n50
b11100010 n51
b11001110 n52
b00111111 n53
b11101001 n54
b10011001 n55
b0 n56
b10011001 n57
b11101001 n58
b00111111 n59
b11001110 n60
b11100010 n61
b10110001 n62
b00000000 n64
b0 n65
b0000000000000000000 n66
b0 n67
b1111111100011100111 n68
b0000000010110000010 n69
b1111111000000101110 n70
b0000001001111101111 n71
b0000000010000111001 n72
b1111111011010111111 n73
b0 n74
b1111111111001101001 n75
b1111110111010010111 n76
b0000000001010000110 n77
b0000000011010111111 n78
b1111111110101111110 n79
b10110001 n80
b11100010 n81
b11001110 n82
b00111111 n83
b11101001 n84
b10011001 n85
b0 n86
b0000000000000000000 n87
b0000000000000000000 n88
b0 n89
b0 n90
b00000000 n91
b0 n92
b0 n93
b00000001 n94
#5
b0 n0
b0 n20
b0 n63
#10
1!
b00000000000000000000000000000001 t
b1 n0
b1 n20
b1 n63
b1111111110101111110 n1
b0 n2
b0000001000000000111 n3
b1111110110101110111 n4
b00011010 n5
b11010001 n6
b00010000 n7
b11101101 n8
b00001001 n9
b10000111 n10
b0 n11
b0 n12
b1111111110101111110 n13
b10000111 n14
b00001001 n15
b11101101 n16
b00010000 n17
b11010001 n18
b00011010 n19
b00000000 n21
b0 n22
b0000000000000000000 n23
b0 n24
b0000000001001010110 n25
b0000000100010100001 n26
b0000000010100010000 n27
b1111111100111111101 n28
b1111111111001011001 n29
b1111111010100100001 n30
b0 n31
b0000001000000000111 n32
b0000000101011110111 n33
b0000001000000000111 n34
b1111110110101110111 n35
b1111111100001010110 n36
b1111110110101110111 n37
b00011010 n38
b11010001 n39
b00010000 n40
b11101101 n41
b00001001 n42
b10000111 n43
b0 n44
b0 n45
b0000000000000000000 n46
b0 n47
b1111111110101111110 n48
b0 n49
b10110001 n50
b11100010 n51
b11001110 n52
b00111111 n53
b11101001 n54
b10011001 n55
b0 n56
b10011001 n57
b11101001 n58
b00111111 n59
b11001110 n60
b11100010 n61
b10110001 n62
b00000000 n64
b0 n65
b1111111110101111110 n66
b0 n67
b1111111100011100111 n68
b0000000010110000010 n69
b1111111000000101110 n70
b0000001001111101111 n71
b0000000010000111001 n72
b1111111011010111111 n73
b0 n74
b1111111111001101001 n75
b1111110111010010111 n76
b0000000001010000110 n77
b0000000011010111111 n78
b1111111110101111110 n79
b10110001 n80
b11100010 n81
b11001110 n82
b00111111 n83
b11101001 n84
b10011001 n85
b0 n86
b1111111110101111110 n87
b0000000000000000000 n88
b0 n89
b0 n90
b00000000 n91
b0 n92
b0 n93
b00000001 n94
#15
b0 n0
b0 n20
b0 n63
#20
1!
b00000000000000000000000000000010 t
b1 n0
b1 n20
b1 n63
b1111111110101111110 n1
b0 n2
b0000001000000000111 n3
b1111110110101110111 n4
b00011010 n5
b11010001 n6
b00010000 n7
b11101101 n8
b00001001 n9
b10000111 n10
b0 n11
b0 n12
b1111111110101111110 n13
b10000111 n14
b00001001 n15
b11101101 n16
b00010000 n17
b11010001 n18
b00011010 n19
b00000000 n21
b0 n22
b1111111110101111110 n23
b0 n24
b0000000001001010110 n25
b0000000100010100001 n26
b0000000010100010000 n27
b1111111100111111101 n28
b1111111111001011001 n29
b1111111010100100001 n30
b0 n31
b0000001000000000111 n32
b0000000101011110111 n33
b0000001000000000111 n34
b1111110110101110111 n35
b1111111100001010110 n36
b1111110110101110111 n37
b00011010 n38
b11010001 n39
b00010000 n40
b11101101 n41
b00001001 n42
b10000111 n43
b0 n44
b0 n45
b1111111110101111110 n46
b0 n47
b1111111110101111110 n48
b0 n49
b10110001 n50
b11100010 n51
b11001110 n52
b00111111 n53
b11101001 n54
b10011001 n55
b0 n56
b10011001 n57
b11101001 n58
b00111111 n59
b11001110 n60
b11100010 n61
b10110001 n62
b00000000 n64
b0 n65
b1111111110101111110 n66
b0 n67
b1111111100011100111 n68
b0000000010110000010 n69
b1111111000000101110 n70
b0000001001111101111 n71
b0000000010000111001 n72
b1111111011010111111 n73
b0 n74
b1111111111001101001 n75
b1111110111010010111 n76
b0000000001010000110 n77
b0000000011010111111 n78
b1111111110101111110 n79
b10110001 n80
b11100010 n81
b11001110 n82
b00111111 n83
b11101001 n84
b10011001 n85
b0 n86
b1111111110101111110 n87
b1111111110101111110 n88
b0 n89
b0 n90
b00000000 n91
b0 n92
b0 n93
b00000001 n94
#25
b0 n0
b0 n20
b0 n63
#30
1!
b00000000000000000000000000000011 t
b1 n0
b1 n20
b1 n63
b1111111110101111110 n1
b0 n2
b0000001000000000111 n3
b1111110110101110111 n4
b00011010 n5
b11010001 n6
b00010000 n7
b11101101 n8
b00001001 n9
b10000111 n10
b0 n11
b0 n12
b1111111110101111110 n13
b10000111 n14
b00001001 n15
b11101101 n16
b00010000 n17
b11010001 n18
b00011010 n19
b00000000 n21
b0 n22
b1111111110101111110 n23
b0 n24
b0000000001001010110 n25
b0000000100010100001 n26
b0000000010100010000 n27
b1111111100111111101 n28
b1111111111001011001 n29
b1111111010100100001 n30
b0 n31
b0000001000000000111 n32
b0000000101011110111 n33
b0000001000000000111 n34
b1111110110101110111 n35
b1111111100001010110 n36
b1111110110101110111 n37
b00011010 n38
b11010001 n39
b00010000 n40
b11101101 n41
b00001001 n42
b10000111 n43
b0 n44
b0 n45
b1111111110101111110 n46
b0 n47
b1111111110101111110 n48
b0 n49
b10110001 n50
b11100010 n51
b11001110 n52
b00111111 n53
b11101001 n54
b10011001 n55
b0 n56
b10011001 n57
b11101001 n58
b00111111 n59
b11001110 n60
b11100010 n61
b10110001 n62
b00000000 n64
b0 n65
b1111111110101111110 n66
b0 n67
b1111111100011100111 n68
b0000000010110000010 n69
b1111111000000101110 n70
b0000001001111101111 n71
b0000000010000111001 n72
b1111111011010111111 n73
b0 n74
b1111111111001101001 n75
b1111110111010010111 n76
b0000000001010000110 n77
b0000000011010111111 n78
b1111111110101111110 n79
b10110001 n80
b11100010 n81
b11001110 n82
b00111111 n83
b11101001 n84
b10011001 n85
b0 n86
b1111111110101111110 n87
b1111111110101111110 n88
b0 n89
b0 n90
b00000000 n91
b0 n92
b0 n93
b00000001 n94
#35
b0 n0
b0 n20
b0 n63
#40
1!
b00000000000000000000000000000100 t
b1 n0
b1 n20
b1 n63
b1111111110101111110 n1
b0 n2
b0000001000000000111 n3
b1111110110101110111 n4
b00011010 n5
b11010001 n6
b00010000 n7
b11101101 n8
b00001001 n9
b10000111 n10
b0 n11
b0 n12
b1111111110101111110 n13
b10000111 n14
b00001001 n15
b11101101 n16
b00010000 n17
b11010001 n18
b00011010 n19
b00000000 n21
b0 n22
b1111111110101111110 n23
b0 n24
b0000000001001010110 n25
b0000000100010100001 n26
b0000000010100010000 n27
b1111111100111111101 n28
b1111111111001011001 n29
b1111111010100100001 n30
b0 n31
b0000001000000000111 n32
b0000000101011110111 n33
b0000001000000000111 n34
b1111110110101110111 n35
b1111111100001010110 n36
b1111110110101110111 n37
b00011010 n38
b11010001 n39
b00010000 n40
b11101101 n41
b00001001 n42
b10000111 n43
b0 n44
b0 n45
b1111111110101111110 n46
b0 n47
b1111111110101111110 n48
b0 n49
b10110001 n50
b11100010 n51
b11001110 n52
b00111111 n53
b11101001 n54
b10011001 n55
b0 n56
b10011001 n57
b11101001 n58
b00111111 n59
b11001110 n60
b11100010 n61
b10110001 n62
b00000000 n64
b0 n65
b1111111110101111110 n66
b0 n67
b1111111100011100111 n68
b0000000010110000010 n69
b1111111000000101110 n70
b0000001001111101111 n71
b0000000010000111001 n72
b1111111011010111111 n73
b0 n74
b1111111111001101001 n75
b1111110111010010111 n76
b0000000001010000110 n77
b0000000011010111111 n78
b1111111110101111110 n79
b10110001 n80
b11100010 n81
b11001110 n82
b00111111 n83
b11101001 n84
b10011001 n85
b0 n86
b1111111110101111110 n87
b1111111110101111110 n88
b0 n89
b0 n90
b00000000 n91
b0 n92
b0 n93
b00000001 n94
#45
b0 n0
b0 n20
b0 n63
#50
1!
b00000000000000000000000000000101 t
b1 n0
b1 n20
b1 n63
b1111111110101111110 n1
b0 n2
b0000001000000000111 n3
b1111110110101110111 n4
b00011010 n5
b11010001 n6
b00010000 n7
b11101101 n8
b00001001 n9
b10000111 n10
b0 n11
b0 n12
b1111111110101111110 n13
b10000111 n14
b00001001 n15
b11101101 n16
b00010000 n17
b11010001 n18
b00011010 n19
b00000000 n21
b0 n22
b1111111110101111110 n23
b0 n24
b0000000001001010110 n25
b0000000100010100001 n26
b0000000010100010000 n27
b1111111100111111101 n28
b1111111111001011001 n29
b1111111010100100001 n30
b0 n31
b0000001000000000111 n32
b0000000101011110111 n33
b0000001000000000111 n34
b1111110110101110111 n35
b1111111100001010110 n36
b1111110110101110111 n37
b00011010 n38
b11010001 n39
b00010000 n40
b11101101 n41
b00001001 n42
b10000111 n43
b0 n44
b0 n45
b1111111110101111110 n46
b0 n47
b1111111110101111110 n48
b0 n49
b10110001 n50
b11100010 n51
b11001110 n52
b00111111 n53
b11101001 n54
b10011001 n55
b0 n56
b10011001 n57
b11101001 n58
b00111111 n59
b11001110 n60
b11100010 n61
b10110001 n62
b00000000 n64
b0 n65
b1111111110101111110 n66
b0 n67
b1111111100011100111 n68
b0000000010110000010 n69
b1111111000000101110 n70
b0000001001111101111 n71
b0000000010000111001 n72
b1111111011010111111 n73
b0 n74
b1111111111001101001 n75
b1111110111010010111 n76
b0000000001010000110 n77
b0000000011010111111 n78
b1111111110101111110 n79
b10110001 n80
b11100010 n81
b11001110 n82
b00111111 n83
b11101001 n84
b10011001 n85
b0 n86
b1111111110101111110 n87
b1111111110101111110 n88
b0 n89
b0 n90
b00000000 n91
b0 n92
b0 n93
b00000001 n94
#55
b0 n0
b0 n20
b0 n63
#60
1!
b00000000000000000000000000000110 t
b1 n0
b1 n20
b1 n63
b1111111110101111110 n1
b0 n2
b0000001000000000111 n3
b1111110110101110111 n4
b00011010 n5
b11010001 n6
b00010000 n7
b11101101 n8
b00001001 n9
b10000111 n10
b0 n11
b0 n12
b1111111110101111110 n13
b10000111 n14
b00001001 n15
b11101101 n16
b00010000 n17
b11010001 n18
b00011010 n19
b00000000 n21
b0 n22
b1111111110101111110 n23
b0 n24
b0000000001001010110 n25
b0000000100010100001 n26
b0000000010100010000 n27
b1111111100111111101 n28
b1111111111001011001 n29
b1111111010100100001 n30
b0 n31
b0000001000000000111 n32
b0000000101011110111 n33
b0000001000000000111 n34
b1111110110101110111 n35
b1111111100001010110 n36
b1111110110101110111 n37
b00011010 n38
b11010001 n39
b00010000 n40
b11101101 n41
b00001001 n42
b10000111 n43
b0 n44
b0 n45
b1111111110101111110 n46
b0 n47
b1111111110101111110 n48
b0 n49
b10110001 n50
b11100010 n51
b11001110 n52
b00111111 n53
b11101001 n54
b10011001 n55
b0 n56
b10011001 n57
b11101001 n58
b00111111 n59
b11001110 n60
b11100010 n61
b10110001 n62
b00000000 n64
b0 n65
b1111111110101111110 n66
b0 n67
b1111111100011100111 n68
b0000000010110000010 n69
b1111111000000101110 n70
b0000001001111101111 n71
b0000000010000111001 n72
b1111111011010111111 n73
b0 n74
b1111111111001101001 n75
b1111110111010010111 n76
b0000000001010000110 n77
b0000000011010111111 n78
b1111111110101111110 n79
b10110001 n80
b11100010 n81
b11001110 n82
b00111111 n83
b11101001 n84
b10011001 n85
b0 n86
b1111111110101111110 n87
b1111111110101111110 n88
b0 n89
b0 n90
b00000000 n91
b0 n92
b0 n93
b00000001 n94
#65
b0 n0
b0 n20
b0 n63
#70
1!
b00000000000000000000000000000111 t
b1 n0
b1 n20
b1 n63
b1111111110101111110 n1
b0 n2
b0000001000000000111 n3
b1111110110101110111 n4
b00011010 n5
b11010001 n6
b00010000 n7
b11101101 n8
b00001001 n9
b10000111 n10
b0 n11
b0 n12
b1111111110101111110 n13
b10000111 n14
b00001001 n15
b11101101 n16
b00010000 n17
b11010001 n18
b00011010 n19
b00000000 n21
b0 n22
b1111111110101111110 n23
b0 n24
b0000000001001010110 n25
b0000000100010100001 n26
b0000000010100010000 n27
b1111111100111111101 n28
b1111111111001011001 n29
b1111111010100100001 n30
b0 n31
b0000001000000000111 n32
b0000000101011110111 n33
b0000001000000000111 n34
b1111110110101110111 n35
b1111111100001010110 n36
b1111110110101110111 n37
b00011010 n38
b11010001 n39
b00010000 n40
b11101101 n41
b00001001 n42
b10000111 n43
b0 n44
b0 n45
b1111111110101111110 n46
b0 n47
b1111111110101111110 n48
b0 n49
b10110001 n50
b11100010 n51
b11001110 n52
b00111111 n53
b11101001 n54
b10011001 n55
b0 n56
b10011001 n57
b11101001 n58
b00111111 n59
b11001110 n60
b11100010 n61
b10110001 n62
b00000000 n64
b0 n65
b1111111110101111110 n66
b0 n67
b1111111100011100111 n68
b0000000010110000010 n69
b1111111000000101110 n70
b0000001001111101111 n71
b0000000010000111001 n72
b1111111011010111111 n73
b0 n74
b1111111111001101001 n75
b1111110111010010111 n76
b0000000001010000110 n77
b0000000011010111111 n78
b1111111110101111110 n79
b10110001 n80
b11100010 n81
b11001110 n82
b00111111 n83
b11101001 n84
b10011001 n85
b0 n86
b1111111110101111110 n87
b1111111110101111110 n88
b0 n89
b0 n90
b00000000 n91
b0 n92
b0 n93
b00000001 n94
#75
b0 n0
b0 n20
b0 n63
#80
1!
b00000000000000000000000000001000 t
b1 n0
b1 n20
b1 n63
b1111111110101111110 n1
b0 n2
b0000001000000000111 n3
b1111110110101110111 n4
b00011010 n5
b11010001 n6
b00010000 n7
b11101101 n8
b00001001 n9
b10000111 n10
b0 n11
b0 n12
b1111111110101111110 n13
b10000111 n14
b00001001 n15
b11101101 n16
b00010000 n17
b11010001 n18
b00011010 n19
b00000000 n21
b0 n22
b1111111110101111110 n23
b0 n24
b0000000001001010110 n25
b0000000100010100001 n26
b0000000010100010000 n27
b1111111100111111101 n28
b1111111111001011001 n29
b1111111010100100001 n30
b0 n31
b0000001000000000111 n32
b0000000101011110111 n33
b0000001000000000111 n34
b1111110110101110111 n35
b1111111100001010110 n36
b1111110110101110111 n37
b00011010 n38
b11010001 n39
b00010000 n40
b11101101 n41
b00001001 n42
b10000111 n43
b0 n44
b0 n45
b1111111110101111110 n46
b0 n47
b1111111110101111110 n48
b0 n49
b10110001 n50
b11100010 n51
b11001110 n52
b00111111 n53
b11101001 n54
b10011001 n55
b0 n56
b10011001 n57
b11101001 n58
b00111111 n59
b11001110 n60
b11100010 n61
b10110001 n62
b00000000 n64
b0 n65
b1111111110101111110 n66
b0 n67
b1111111100011100111 n68
b0000000010110000010 n69
b1111111000000101110 n70
b0000001001111101111 n71
b0000000010000111001 n72
b1111111011010111111 n73
b0 n74
b1111111111001101001 n75
b1111110111010010111 n76
b0000000001010000110 n77
b0000000011010111111 n78
b1111111110101111110 n79
b10110001 n80
b11100010 n81
b11001110 n82
b00111111 n83
b11101001 n84
b10011001 n85
b0 n86
b1111111110101111110 n87
b1111111110101111110 n88
b0 n89
b0 n90
b00000000 n91
b0 n92
b0 n93
b00000001 n94
#85
b0 n0
b0 n20
b0 n63
#90
1!
b00000000000000000000000000001001 t
b1 n0
b1 n20
b1 n63
b1111111110101111110 n1
b0 n2
b0000001000000000111 n3
b1111110110101110111 n4
b00011010 n5
b11010001 n6
b00010000 n7
b11101101 n8
b00001001 n9
b10000111 n10
b0 n11
b0 n12
b1111111110101111110 n13
b10000111 n14
b00001001 n15
b11101101 n16
b00010000 n17
b11010001 n18
b00011010 n19
b00000000 n21
b0 n22
b1111111110101111110 n23
b0 n24
b0000000001001010110 n25
b0000000100010100001 n26
b0000000010100010000 n27
b1111111100111111101 n28
b1111111111001011001 n29
b1111111010100100001 n30
b0 n31
b0000001000000000111 n32
b0000000101011110111 n33
b0000001000000000111 n34
b1111110110101110111 n35
b1111111100001010110 n36
b1111110110101110111 n37
b00011010 n38
b11010001 n39
b00010000 n40
b11101101 n41
b00001001 n42
b10000111 n43
b0 n44
b0 n45
b1111111110101111110 n46
b0 n47
b1111111110101111110 n48
b0 n49
b10110001 n50
b11100010 n51
b11001110 n52
b00111111 n53
b11101001 n54
b10011001 n55
b0 n56
b10011001 n57
b11101001 n58
b00111111 n59
b11001110 n60
b11100010 n61
b10110001 n62
b00000000 n64
b0 n65
b1111111110101111110 n66
b0 n67
b1111111100011100111 n68
b0000000010110000010 n69
b1111111000000101110 n70
b0000001001111101111 n71
b0000000010000111001 n72
b1111111011010111111 n73
b0 n74
b1111111111001101001 n75
b1111110111010010111 n76
b0000000001010000110 n77
b0000000011010111111 n78
b1111111110101111110 n79
b10110001 n80
b11100010 n81
b11001110 n82
b00111111 n83
b11101001 n84
b10011001 n85
b0 n86
b1111111110101111110 n87
b1111111110101111110 n88
b0 n89
b0 n90
b00000000 n91
b0 n92
b0 n93
b00000001 n94
#95
b0 n0
b0 n20
b0 n63
